Workbook

Sheet Assumptions
A1: Meridian Solar IPP — 50 MW
A2: Assumptions Tab — all model inputs live here
A3: Colour key: BLUE = hardcoded input | BLACK = formula / calculation | GREEN = link from another tab
A4: All currency in USD millions unless stated otherwise.
A6: 1. PROJECT & TECHNICAL | B6: Value | C6: Unit | D6: Note / source
A7: Installed capacity | B7: 50 | C7: MW | D7: Case assumption
A8: Hours per year | B8: 8760 | C8: hours | D8: Case assumption (365 x 24)
A9: Net capacity factor | B9: 0.21 | C9: % | D9: Applied to gross generation — key sensitivity driver
A10: Gross generation at 100% capacity factor | B10: =B7*1000*B8/1000000 -> 438 | C10: GWh | D10: = Capacity (MW) x 1,000 x hours
A11: Net annual generation | B11: =B10*B9 -> 91.98 | C11: GWh | D11: = Gross generation x net capacity factor
A12: Net annual generation | B12: =B11*1000000 -> 91980000 | C12: kWh | D12: Flat across all 20 years — no panel degradation assumed (see note below)
A14: 2. CONSTRUCTION & CAPEX | B14: Value | C14: Unit | D14: Note / source
A15: Total construction cost (capex) | B15: 60 | C15: USD m | D15: Incurred evenly over a 12-month build
A16: Implied capex per MW | B16: =B15/B7 -> 1.2 | C16: USD m / MW | D16: Sanity check — in line with utility-scale solar benchmarks
A17: Construction period | B17: 12 | C17: months | D17: Single construction year (Year 0 = calendar 2026)
A18: Construction start | B18: 46023 | C18: date | D18: Assumption — 12 months before COD
A19: Commercial operation date (COD) | B19: 46388 | C19: date | D19: Year 1 of operations
A20: Operating life / PPA term | B20: 20 | C20: years | D20: 20-year take-or-pay PPA
A22: 3. REVENUE & OPERATING COSTS | B22: Value | C22: Unit | D22: Note / source
A23: PPA tariff — Year 1 | B23: 0.075 | C23: USD / kWh | D23: 20-year take-or-pay PPA — key sensitivity driver
A24: Tariff escalation (from Year 2) | B24: 0.015 | C24: % p.a. | D24: Contractual indexation
A25: Implied Year 1 revenue | B25: =B12*B23/1000000 -> 6.8985 | C25: USD m | D25: Cross-check against Model tab
A26: Operating cost — Year 1 | B26: 1.2 | C26: USD m | D26: O&M, insurance, land, admin
A27: Operating cost escalation (from Year 2) | B27: 0.03 | C27: % p.a. | D27: Assumed local inflation proxy
A28: Implied Year 1 EBITDA margin | B28: =(B25-B26)/B25 -> 0.82604914 | C28: % | D28: Sanity check — typical for solar IPP with low variable cost
A30: 4. DEPRECIATION, TAX & DISCOUNTING | B30: Value | C30: Unit | D30: Note / source
A31: Depreciation life (straight-line) | B31: 20 | C31: years | D31: Asset fully depreciated over the PPA term
A32: Annual depreciation charge | B32: =B15/B31 -> 3 | C32: USD m | D32: = Capex / depreciation life
A33: Corporate tax rate | B33: 0.3 | C33: % | D33: Tax paid in the year incurred; no loss carry-forward modelled
A34: Project discount rate (unlevered WACC) | B34: 0.1 | C34: % | D34: Prescribed by the case for project NPV
A36: 5. SECTION C — Domestic Infrastructure Fund SENIOR DEBT TERMS | B36: Value | C36: Unit | D36: Note / source
A37: Maximum gearing (debt as % of project cost) | B37: 0.7 | C37: % | D37: DIF cap — 70:30 debt:equity
A38: Debt tenor from COD | B38: 15 | C38: years | D38: DIF maximum tenor
A39: Interest rate on drawn senior debt | B39: 0.08 | C39: % p.a. | D39: DIF term sheet
A40: Minimum DSCR covenant | B40: 1.3 | C40: x | D40: Hard covenant — must be met in every period
A41: Target sculpting DSCR | B41: 1.3 | C41: x | D41: Debt service sculpted to this DSCR; set = covenant to maximise capacity
A42: DSRA — months of forward debt service | B42: 6 | C42: months | D42: Funded at COD from equity; released on final repayment
A43: Cash sweep — % of surplus cash | B43: 0.5 | C43: % | D43: Applied after scheduled debt service, until debt repaid
A44: Cash sweep switch (1 = on, 0 = off) | B44: 1 | C44: flag | D44: Toggle to show the schedule with and without the sweep
A45: Maximum debt by gearing cap | B45: =B37*B15 -> 42 | C45: USD m | D45: = 70% x total project cost
A47: 6. STATED ASSUMPTIONS & JUDGEMENTS (where the case is silent)
A48: 1. Periodicity: annual periods. Year 0 = construction (calendar 2026); Years 1-20 = operations (2027-2046). Cash flows treated as arising at period end.
A49: 2. Capex is incurred evenly over the 12-month build, i.e. wholly within Year 0. No interest during construction or capitalised financing costs are charged, as the case gives no drawdown profile within the build.
A50: 3. No panel degradation is assumed — the case specifies a single net capacity factor of 21% and no degradation rate. In practice 0.4-0.5% p.a. would apply; this is flagged as an upside risk to CFADS in later years.
A51: 4. Take-or-pay PPA: 100% of net generation is deemed sold each year, so there is no volume risk and no receivables build. Working capital is therefore assumed nil throughout.
A52: 5. No maintenance capex, inverter replacement reserve or decommissioning cost is modelled — none is given. Real-world inverter replacement around Year 10-12 would be a genuine CFADS drag.
A53: 6. Tax is computed on an unlevered basis in the Model tab so that CFADS is clean and pre-financing. The interest tax shield is calculated separately on the Debt tab and credited to equity cash flow, which keeps the Section A model valid standalone.
A54: 7. No tax losses arise on the base case, so no loss carry-forward mechanic is needed. A check row on the Model tab flags if taxable profit ever turns negative.
A55: 8. Total project cost for the gearing test is taken as capex of USD 60.0m. The DSRA is funded by equity at COD and sits outside the gearing base — stated explicitly because it changes the debt cap.
A56: 9. All figures are nominal USD. No FX exposure is modelled: the PPA, capex and DIF debt are all assumed USD-denominated. Local-currency tariff settlement would introduce FX risk (flagged in Section C risks).
A57: 10. Terminal / residual value is nil at the end of Year 20. The asset is fully depreciated and the PPA expires; any merchant-tail value is treated as unmodelled upside.

Sheet Model
A1: Meridian Solar IPP — PROJECT FINANCE MODEL (SECTION A)
A2: Unlevered project cash flows. All figures USD m unless stated. Green = link to Assumptions tab.
A4: Period (year from COD) | B4: Unit | C4: 0 | D4: =C4+1 -> 1 | E4: =D4+1 -> 2 | F4: =E4+1 -> 3 | G4: =F4+1 -> 4 | H4: =G4+1 -> 5 | I4: =H4+1 -> 6 | J4: =I4+1 -> 7 | K4: =J4+1 -> 8 | ... W4: =V4+1 -> 20
A5: Calendar year | C5: =YEAR(Assumptions!$B$18) -> 2026 | D5: =C5+1 -> 2027 | E5: =D5+1 -> 2028 | F5: =E5+1 -> 2029 | G5: =F5+1 -> 2030 | H5: =G5+1 -> 2031 | I5: =H5+1 -> 2032 | J5: =I5+1 -> 2033 | K5: =J5+1 -> 2034 | ... W5: =V5+1 -> 2046
A6: Phase | C6: =IF(C4=0,"Construction","Operations") -> Construction | D6: =IF(D4=0,"Construction","Operations") -> Operations | E6: =IF(E4=0,"Construction","Operations") -> Operations | F6: =IF(F4=0,"Construction","Operations") -> Operations | G6: =IF(G4=0,"Construction","Operations") -> Operations | H6: =IF(H4=0,"Construction","Operations") -> Operations | I6: =IF(I4=0,"Construction","Operations") -> Operations | J6: =IF(J4=0,"Construction","Operations") -> Operations | ... W6: =IF(W4=0,"Construction","Operations") -> Operations
A7: Operating period flag | C7: =IF(AND(C4>=1,C4<=Assumptions!$B$20),1,0) -> 0 | D7: =IF(AND(D4>=1,D4<=Assumptions!$B$20),1,0) -> 1 | E7: =IF(AND(E4>=1,E4<=Assumptions!$B$20),1,0) -> 1 | F7: =IF(AND(F4>=1,F4<=Assumptions!$B$20),1,0) -> 1 | G7: =IF(AND(G4>=1,G4<=Assumptions!$B$20),1,0) -> 1 | H7: =IF(AND(H4>=1,H4<=Assumptions!$B$20),1,0) -> 1 | I7: =IF(AND(I4>=1,I4<=Assumptions!$B$20),1,0) -> 1 | J7: =IF(AND(J4>=1,J4<=Assumptions!$B$20),1,0) -> 1 | ... W7: =IF(AND(W4>=1,W4<=Assumptions!$B$20),1,0) -> 1
A9: REVENUE BUILD
A10: Net generation | B10: GWh | C10: =C7*Assumptions!$B$11 -> 0 | D10: =D7*Assumptions!$B$11 -> 91.98 | E10: =E7*Assumptions!$B$11 -> 91.98 | F10: =F7*Assumptions!$B$11 -> 91.98 | G10: =G7*Assumptions!$B$11 -> 91.98 | H10: =H7*Assumptions!$B$11 -> 91.98 | I10: =I7*Assumptions!$B$11 -> 91.98 | J10: =J7*Assumptions!$B$11 -> 91.98 | ... W10: =W7*Assumptions!$B$11 -> 91.98
A11: PPA tariff | B11: USD/kWh | C11: =IF(C7=0,0,Assumptions!$B$23*(1+Assumptions!$B$24)^(C4-1)) -> 0 | D11: =IF(D7=0,0,Assumptions!$B$23*(1+Assumptions!$B$24)^(D4-1)) -> 0.075 | E11: =IF(E7=0,0,Assumptions!$B$23*(1+Assumptions!$B$24)^(E4-1)) -> 0.076125 | F11: =IF(F7=0,0,Assumptions!$B$23*(1+Assumptions!$B$24)^(F4-1)) -> 0.077266875 | G11: =IF(G7=0,0,Assumptions!$B$23*(1+Assumptions!$B$24)^(G4-1)) -> 0.078425878 | H11: =IF(H7=0,0,Assumptions!$B$23*(1+Assumptions!$B$24)^(H4-1)) -> 0.079602266 | I11: =IF(I7=0,0,Assumptions!$B$23*(1+Assumptions!$B$24)^(I4-1)) -> 0.0807963 | J11: =IF(J7=0,0,Assumptions!$B$23*(1+Assumptions!$B$24)^(J4-1)) -> 0.082008245 | ... W11: =IF(W7=0,0,Assumptions!$B$23*(1+Assumptions!$B$24)^(W4-1)) -> 0.099521306
A12: Revenue | B12: USD m | C12: =C10*C11 -> 0 | D12: =D10*D11 -> 6.8985 | E12: =E10*E11 -> 7.0019775 | F12: =F10*F11 -> 7.1070072 | G12: =G10*G11 -> 7.2136123 | H12: =H10*H11 -> 7.3218165 | I12: =I10*I11 -> 7.4316437 | J12: =J10*J11 -> 7.5431184 | ... W12: =W10*W11 -> 9.1539697
A14: OPERATING COSTS
A15: Operating cost (O&M, insurance, admin) | B15: USD m | C15: =-IF(C7=0,0,Assumptions!$B$26*(1+Assumptions!$B$27)^(C4-1)) -> 0 | D15: =-IF(D7=0,0,Assumptions!$B$26*(1+Assumptions!$B$27)^(D4-1)) -> -1.2 | E15: =-IF(E7=0,0,Assumptions!$B$26*(1+Assumptions!$B$27)^(E4-1)) -> -1.236 | F15: =-IF(F7=0,0,Assumptions!$B$26*(1+Assumptions!$B$27)^(F4-1)) -> -1.27308 | G15: =-IF(G7=0,0,Assumptions!$B$26*(1+Assumptions!$B$27)^(G4-1)) -> -1.3112724 | H15: =-IF(H7=0,0,Assumptions!$B$26*(1+Assumptions!$B$27)^(H4-1)) -> -1.3506106 | I15: =-IF(I7=0,0,Assumptions!$B$26*(1+Assumptions!$B$27)^(I4-1)) -> -1.3911289 | J15: =-IF(J7=0,0,Assumptions!$B$26*(1+Assumptions!$B$27)^(J4-1)) -> -1.4328628 | ... W15: =-IF(W7=0,0,Assumptions!$B$26*(1+Assumptions!$B$27)^(W4-1)) -> -2.1042073
A17: EBITDA | B17: USD m | C17: =C12+C15 -> 0 | D17: =D12+D15 -> 5.6985 | E17: =E12+E15 -> 5.7659775 | F17: =F12+F15 -> 5.8339272 | G17: =G12+G15 -> 5.9023399 | H17: =H12+H15 -> 5.9712059 | I17: =I12+I15 -> 6.0405148 | J17: =J12+J15 -> 6.1102556 | ... W17: =W12+W15 -> 7.0497625
A18: EBITDA margin | B18: % | C18: =IF(C12=0,0,C17/C12) -> 0 | D18: =IF(D12=0,0,D17/D12) -> 0.82604914 | E18: =IF(E12=0,0,E17/E12) -> 0.82347844 | F18: =IF(F12=0,0,F17/F12) -> 0.82086975 | G18: =IF(G12=0,0,G17/G12) -> 0.8182225 | H18: =IF(H12=0,0,H17/H12) -> 0.81553613 | I18: =IF(I12=0,0,I17/I12) -> 0.81281007 | J18: =IF(J12=0,0,J17/J12) -> 0.81004371 | ... W18: =IF(W12=0,0,W17/W12) -> 0.77013172
A20: DEPRECIATION, TAX & ASSET BASE
A21: Opening net book value | B21: USD m | C21: 0 | D21: =C24 -> 60 | E21: =D24 -> 57 | F21: =E24 -> 54 | G21: =F24 -> 51 | H21: =G24 -> 48 | I21: =H24 -> 45 | J21: =I24 -> 42 | K21: =J24 -> 39 | ... W21: =V24 -> 3
A22: Add: capex additions | B22: USD m | C22: =IF(C4=0,Assumptions!$B$15,0) -> 60 | D22: =IF(D4=0,Assumptions!$B$15,0) -> 0 | E22: =IF(E4=0,Assumptions!$B$15,0) -> 0 | F22: =IF(F4=0,Assumptions!$B$15,0) -> 0 | G22: =IF(G4=0,Assumptions!$B$15,0) -> 0 | H22: =IF(H4=0,Assumptions!$B$15,0) -> 0 | I22: =IF(I4=0,Assumptions!$B$15,0) -> 0 | J22: =IF(J4=0,Assumptions!$B$15,0) -> 0 | ... W22: =IF(W4=0,Assumptions!$B$15,0) -> 0
A23: Less: depreciation charge | B23: USD m | C23: =-IF(AND(C4>=1,C4<=Assumptions!$B$31),Assumptions!$B$32,0) -> 0 | D23: =-IF(AND(D4>=1,D4<=Assumptions!$B$31),Assumptions!$B$32,0) -> -3 | E23: =-IF(AND(E4>=1,E4<=Assumptions!$B$31),Assumptions!$B$32,0) -> -3 | F23: =-IF(AND(F4>=1,F4<=Assumptions!$B$31),Assumptions!$B$32,0) -> -3 | G23: =-IF(AND(G4>=1,G4<=Assumptions!$B$31),Assumptions!$B$32,0) -> -3 | H23: =-IF(AND(H4>=1,H4<=Assumptions!$B$31),Assumptions!$B$32,0) -> -3 | I23: =-IF(AND(I4>=1,I4<=Assumptions!$B$31),Assumptions!$B$32,0) -> -3 | J23: =-IF(AND(J4>=1,J4<=Assumptions!$B$31),Assumptions!$B$32,0) -> -3 | ... W23: =-IF(AND(W4>=1,W4<=Assumptions!$B$31),Assumptions!$B$32,0) -> -3
A24: Closing net book value | B24: USD m | C24: =C21+C22+C23 -> 60 | D24: =D21+D22+D23 -> 57 | E24: =E21+E22+E23 -> 54 | F24: =F21+F22+F23 -> 51 | G24: =G21+G22+G23 -> 48 | H24: =H21+H22+H23 -> 45 | I24: =I21+I22+I23 -> 42 | J24: =J21+J22+J23 -> 39 | ... W24: =W21+W22+W23 -> 0
A26: EBIT (EBITDA less depreciation) | B26: USD m | C26: =C17+C23 -> 0 | D26: =D17+D23 -> 2.6985 | E26: =E17+E23 -> 2.7659775 | F26: =F17+F23 -> 2.8339272 | G26: =G17+G23 -> 2.9023399 | H26: =H17+H23 -> 2.9712059 | I26: =I17+I23 -> 3.0405148 | J26: =J17+J23 -> 3.1102556 | ... W26: =W17+W23 -> 4.0497625
A27: Tax at corporate rate (unlevered basis) | B27: USD m | C27: =-MAX(0,C26)*Assumptions!$B$33 -> 0 | D27: =-MAX(0,D26)*Assumptions!$B$33 -> -0.80955 | E27: =-MAX(0,E26)*Assumptions!$B$33 -> -0.82979325 | F27: =-MAX(0,F26)*Assumptions!$B$33 -> -0.85017815 | G27: =-MAX(0,G26)*Assumptions!$B$33 -> -0.87070196 | H27: =-MAX(0,H26)*Assumptions!$B$33 -> -0.89136176 | I27: =-MAX(0,I26)*Assumptions!$B$33 -> -0.91215444 | J27: =-MAX(0,J26)*Assumptions!$B$33 -> -0.93307668 | ... W27: =-MAX(0,W26)*Assumptions!$B$33 -> -1.2149287
A28: Check: taxable profit not negative | B28: flag | C28: =IF(C26<0,"LOSS","ok") -> ok | D28: =IF(D26<0,"LOSS","ok") -> ok | E28: =IF(E26<0,"LOSS","ok") -> ok | F28: =IF(F26<0,"LOSS","ok") -> ok | G28: =IF(G26<0,"LOSS","ok") -> ok | H28: =IF(H26<0,"LOSS","ok") -> ok | I28: =IF(I26<0,"LOSS","ok") -> ok | J28: =IF(J26<0,"LOSS","ok") -> ok | ... W28: =IF(W26<0,"LOSS","ok") -> ok
A30: CASH FLOW
A31: EBITDA | B31: USD m | C31: =C17 -> 0 | D31: =D17 -> 5.6985 | E31: =E17 -> 5.7659775 | F31: =F17 -> 5.8339272 | G31: =G17 -> 5.9023399 | H31: =H17 -> 5.9712059 | I31: =I17 -> 6.0405148 | J31: =J17 -> 6.1102556 | ... W31: =W17 -> 7.0497625
A32: Less: cash tax (unlevered) | B32: USD m | C32: =C27 -> 0 | D32: =D27 -> -0.80955 | E32: =E27 -> -0.82979325 | F32: =F27 -> -0.85017815 | G32: =G27 -> -0.87070196 | H32: =H27 -> -0.89136176 | I32: =I27 -> -0.91215444 | J32: =J27 -> -0.93307668 | ... W32: =W27 -> -1.2149287
A33: Less: change in net working capital | B33: USD m | C33: 0 | D33: 0 | E33: 0 | F33: 0 | G33: 0 | H33: 0 | I33: 0 | J33: 0 | K33: 0 | L33: 0 | M33: 0 | N33: 0 | O33: 0 | P33: 0 | Q33: 0 | R33: 0 | S33: 0 | T33: 0 | U33: 0 | V33: 0 | W33: 0
A34: CFADS — CASH FLOW AVAILABLE FOR DEBT SERVICE | B34: USD m | C34: =C31+C32+C33 -> 0 | D34: =D31+D32+D33 -> 4.88895 | E34: =E31+E32+E33 -> 4.9361842 | F34: =F31+F32+F33 -> 4.983749 | G34: =G31+G32+G33 -> 5.0316379 | H34: =H31+H32+H33 -> 5.0798441 | I34: =I31+I32+I33 -> 5.1283604 | J34: =J31+J32+J33 -> 5.1771789 | ... W34: =W31+W32+W33 -> 5.8348337
A36: Less: capex | B36: USD m | C36: =-C22 -> -60 | D36: =-D22 -> 0 | E36: =-E22 -> 0 | F36: =-F22 -> 0 | G36: =-G22 -> 0 | H36: =-H22 -> 0 | I36: =-I22 -> 0 | J36: =-J22 -> 0 | ... W36: =-W22 -> 0
A37: UNLEVERED FREE CASH FLOW (PROJECT FCF) | B37: USD m | C37: =C34+C36 -> -60 | D37: =D34+D36 -> 4.88895 | E37: =E34+E36 -> 4.9361842 | F37: =F34+F36 -> 4.983749 | G37: =G34+G36 -> 5.0316379 | H37: =H34+H36 -> 5.0798441 | I37: =I34+I36 -> 5.1283604 | J37: =J34+J36 -> 5.1771789 | ... W37: =W34+W36 -> 5.8348337
A38: Cumulative unlevered free cash flow | B38: USD m | C38: =C37 -> -60 | D38: =C38+D37 -> -55.11105 | E38: =D38+E37 -> -50.174866 | F38: =E38+F37 -> -45.191117 | G38: =F38+G37 -> -40.159479 | H38: =G38+H37 -> -35.079635 | I38: =H38+I37 -> -29.951274 | J38: =I38+J37 -> -24.774095 | K38: =J38+K37 -> -19.547804 | ... W38: =V38+W37 -> 47.091918
A39: Discount factor at project discount rate | B39: x | C39: =1/(1+Assumptions!$B$34)^C4 -> 1 | D39: =1/(1+Assumptions!$B$34)^D4 -> 0.90909091 | E39: =1/(1+Assumptions!$B$34)^E4 -> 0.82644628 | F39: =1/(1+Assumptions!$B$34)^F4 -> 0.7513148 | G39: =1/(1+Assumptions!$B$34)^G4 -> 0.68301346 | H39: =1/(1+Assumptions!$B$34)^H4 -> 0.62092132 | I39: =1/(1+Assumptions!$B$34)^I4 -> 0.56447393 | J39: =1/(1+Assumptions!$B$34)^J4 -> 0.51315812 | ... W39: =1/(1+Assumptions!$B$34)^W4 -> 0.14864363
A40: PV of unlevered free cash flow | B40: USD m | C40: =C37*C39 -> -60 | D40: =D37*D39 -> 4.4445 | E40: =E37*E39 -> 4.0794911 | F40: =F37*F39 -> 3.7443644 | G40: =G37*G39 -> 3.4366764 | H40: =H37*H39 -> 3.1541835 | I40: =I37*I39 -> 2.8948257 | J40: =J37*J39 -> 2.6567114 | ... W40: =W37*W39 -> 0.86731085
A42: PROJECT RETURNS — UNLEVERED | C42: Value
A43: Project IRR (unlevered) | B43: % | C43: =IRR(C37:W37) -> 0.060665745
A44: Project NPV at discount rate (sum of PV row) | B44: USD m | C44: =SUM(C40:W40) -> -15.678691
A45: Cross-check: NPV via NPV() function | B45: USD m | C45: =C37+NPV(Assumptions!$B$34,D37:W37) -> -15.678691
A46: Check: two NPV methods agree | B46: flag | C46: =IF(ABS(C44-C45)<0.001,"ok","CHECK") -> ok
A47: Simple payback (years from COD, undiscounted) | B47: years | C47: =IF(W38<0,"Not repaid",COUNTIF(D38:W38,"<0")+1) -> 12
A48: Undiscounted cash-on-cash multiple | B48: x | C48: =SUM(D37:W37)/-C37 -> 1.7848653
A49: Total lifetime generation | B49: GWh | C49: =SUM(C10:W10) -> 1839.6
A51: BREAKEVEN ANALYSIS AT THE 10% DISCOUNT RATE | C51: Value
A52: PV of revenue (Years 1-20) | B52: USD m | C52: =SUMPRODUCT($D$39:$W$39,$D$12:$W$12) -> 64.910712
A53: PV of operating cost (Years 1-20) | B53: USD m | C53: =SUMPRODUCT($D$39:$W$39,$D$15:$W$15) -> -12.540567
A54: PV of depreciation tax shield | B54: USD m | C54: =Assumptions!$B$33*Assumptions!$B$32*SUM($D$39:$W$39) -> 7.6622073
A55: Revenue uplift required for NPV = 0 | B55: x | C55: =(Assumptions!$B$15-(1-Assumptions!$B$33)*C53-C54)/((1-Assumptions!$B$33)*C52) -> 1.3450606
A56: Breakeven PPA tariff (capacity factor held at base) | B56: USD/kWh | C56: =Assumptions!$B$23*C55 -> 0.10087955
A57: Breakeven net capacity factor (tariff held at base) | B57: % | C57: =Assumptions!$B$9*C55 -> 0.28246273
A58: Breakeven total capex (revenue held at base) | B58: USD m | C58: =(1-Assumptions!$B$33)*(C52+C53)/(1-Assumptions!$B$33*SUM($D$39:$W$39)/Assumptions!$B$31) -> 42.025962
A59: Check: breakeven tariff reproduces NPV of zero | B59: USD m | C59: =-Assumptions!$B$15+(1-Assumptions!$B$33)*(C52*C55+C53)+C54 -> -1.687539e-14

Sheet Debt
A1: DIF SENIOR DEBT PACKAGE — Meridian Solar IPP (SECTION C)
A2: Debt sized off the Model tab CFADS line. Repayment sculpted to the target DSCR. All figures USD m.
A4: Period (year from COD) | B4: Unit | C4: =Model!C4 -> 0 | D4: =Model!D4 -> 1 | E4: =Model!E4 -> 2 | F4: =Model!F4 -> 3 | G4: =Model!G4 -> 4 | H4: =Model!H4 -> 5 | I4: =Model!I4 -> 6 | J4: =Model!J4 -> 7 | ... W4: =Model!W4 -> 20
A5: Calendar year | C5: =Model!C5 -> 2026 | D5: =Model!D5 -> 2027 | E5: =Model!E5 -> 2028 | F5: =Model!F5 -> 2029 | G5: =Model!G5 -> 2030 | H5: =Model!H5 -> 2031 | I5: =Model!I5 -> 2032 | J5: =Model!J5 -> 2033 | ... W5: =Model!W5 -> 2046
A7: 1. DEBT SIZING — WHICH CONSTRAINT BINDS?
A8: CFADS (link from Model tab) | B8: USD m | C8: =Model!C34 -> 0 | D8: =Model!D34 -> 4.88895 | E8: =Model!E34 -> 4.9361842 | F8: =Model!F34 -> 4.983749 | G8: =Model!G34 -> 5.0316379 | H8: =Model!H34 -> 5.0798441 | I8: =Model!I34 -> 5.1283604 | J8: =Model!J34 -> 5.1771789 | ... W8: =Model!W34 -> 5.8348337
A9: Debt period flag (within tenor) | B9: flag | C9: =IF(AND(C4>=1,C4<=Assumptions!$B$38),1,0) -> 0 | D9: =IF(AND(D4>=1,D4<=Assumptions!$B$38),1,0) -> 1 | E9: =IF(AND(E4>=1,E4<=Assumptions!$B$38),1,0) -> 1 | F9: =IF(AND(F4>=1,F4<=Assumptions!$B$38),1,0) -> 1 | G9: =IF(AND(G4>=1,G4<=Assumptions!$B$38),1,0) -> 1 | H9: =IF(AND(H4>=1,H4<=Assumptions!$B$38),1,0) -> 1 | I9: =IF(AND(I4>=1,I4<=Assumptions!$B$38),1,0) -> 1 | J9: =IF(AND(J4>=1,J4<=Assumptions!$B$38),1,0) -> 1 | ... W9: =IF(AND(W4>=1,W4<=Assumptions!$B$38),1,0) -> 0
A10: Maximum affordable debt service at target DSCR | B10: USD m | C10: =C9*C8/Assumptions!$B$41 -> 0 | D10: =D9*D8/Assumptions!$B$41 -> 3.7607308 | E10: =E9*E8/Assumptions!$B$41 -> 3.7970648 | F10: =F9*F8/Assumptions!$B$41 -> 3.8336531 | G10: =G9*G8/Assumptions!$B$41 -> 3.8704907 | H10: =H9*H8/Assumptions!$B$41 -> 3.9075724 | I10: =I9*I8/Assumptions!$B$41 -> 3.9448926 | J10: =J9*J8/Assumptions!$B$41 -> 3.9824453 | ... W10: =W9*W8/Assumptions!$B$41 -> 0
A11: Discount factor at senior debt interest rate | B11: x | C11: =IF(C9=0,0,1/(1+Assumptions!$B$39)^C4) -> 0 | D11: =IF(D9=0,0,1/(1+Assumptions!$B$39)^D4) -> 0.92592593 | E11: =IF(E9=0,0,1/(1+Assumptions!$B$39)^E4) -> 0.85733882 | F11: =IF(F9=0,0,1/(1+Assumptions!$B$39)^F4) -> 0.79383224 | G11: =IF(G9=0,0,1/(1+Assumptions!$B$39)^G4) -> 0.73502985 | H11: =IF(H9=0,0,1/(1+Assumptions!$B$39)^H4) -> 0.6805832 | I11: =IF(I9=0,0,1/(1+Assumptions!$B$39)^I4) -> 0.63016963 | J11: =IF(J9=0,0,1/(1+Assumptions!$B$39)^J4) -> 0.5834904 | ... W11: =IF(W9=0,0,1/(1+Assumptions!$B$39)^W4) -> 0
A12: PV of maximum affordable debt service | B12: USD m | C12: =C10*C11 -> 0 | D12: =D10*D11 -> 3.4821581 | E12: =E10*E11 -> 3.2553711 | F12: =F10*F11 -> 3.0432774 | G12: =G10*G11 -> 2.8449262 | H12: =H10*H11 -> 2.6594281 | I12: =I10*I11 -> 2.4859515 | J12: =J10*J11 -> 2.3237186 | ... W12: =W10*W11 -> 0
A14: Sizing test results | C14: Value
A15: (a) Maximum debt supported by the 1.30x DSCR covenant | B15: USD m | C15: =SUM(C12:W12) -> 33.973835
A16: (b) Maximum debt supported by the 70% gearing cap | B16: USD m | C16: =Assumptions!$B$45 -> 42
A17: SENIOR DEBT SIZED (lower of a and b) | B17: USD m | C17: =MIN(C15,C16) -> 33.973835
A18: BINDING CONSTRAINT | C18: =IF(C15<C16,"DSCR covenant binds",IF(C15>C16,"70% gearing cap binds","Both bind equally")) -> DSCR covenant binds
A19: Implied gearing (debt / total construction cost) | B19: % | C19: =C17/Assumptions!$B$15 -> 0.56623058
A20: Debt service scaling factor (1.00 if DSCR binds) | B20: x | C20: =C17/C15 -> 1
A21: Resulting DSCR on the sculpted profile | B21: x | C21: =Assumptions!$B$41/C20 -> 1.3
A22: Headroom of sized debt vs gearing cap | B22: USD m | C22: =C16-C17 -> 8.0261652
A24: 2. SOURCES AND USES AT FINANCIAL CLOSE | C24: USD m | D24: % of total
A25: SOURCES
A26: Senior debt — National Infrastructure Fund | C26: =$C$17 -> 33.973835 | D26: =C26/$C$28 -> 0.54902447
A27: Sponsor equity | C27: =C32-C26 -> 27.906531 | D27: =C27/$C$28 -> 0.45097553
A28: Total sources | C28: =SUM(C26:C27) -> 61.880365 | D28: =C28/$C$28 -> 1
A29: USES
A30: Construction capex (EPC, land, grid connection, development) | C30: =Assumptions!$B$15 -> 60 | D30: =C30/$C$32 -> 0.96961289
A31: Debt service reserve account (6 months forward debt service) | C31: =$C$53 -> 1.8803654 | D31: =C31/$C$32 -> 0.030387109
A32: Total uses | C32: =C30+C31 -> 61.880365 | D32: =C32/$C$32 -> 1
A34: Check: total sources = total uses | C34: =IF(ABS(C28-C32)<0.001,"ok","CHECK") -> ok
A35: Debt : equity ratio | C35: =C26/C32 -> 0.54902447 | D35: =C27/C32 -> 0.45097553
A36: Note: the DSRA is funded by sponsor equity at COD and sits outside the 70% gearing base (see Assumptions, note 8).
A38: 3. SENIOR DEBT REPAYMENT SCHEDULE (sculpted to target DSCR, with cash sweep)
A39: Opening balance | B39: USD m | C39: 0 | D39: =C46 -> 33.973835 | E39: =D46 -> 32.366901 | F39: =E46 -> 30.589629 | G39: =F46 -> 28.628098 | H39: =G46 -> 26.467281 | I39: =H46 -> 24.090956 | J39: =I46 -> 21.481606 | K39: =J46 -> 18.620322 | ... W39: =V46 -> 0
A40: Drawdown at financial close | B40: USD m | C40: =IF(C4=0,$C$17,0) -> 33.973835 | D40: =IF(D4=0,$C$17,0) -> 0 | E40: =IF(E4=0,$C$17,0) -> 0 | F40: =IF(F4=0,$C$17,0) -> 0 | G40: =IF(G4=0,$C$17,0) -> 0 | H40: =IF(H4=0,$C$17,0) -> 0 | I40: =IF(I4=0,$C$17,0) -> 0 | J40: =IF(J4=0,$C$17,0) -> 0 | ... W40: =IF(W4=0,$C$17,0) -> 0
A41: Interest accrued at senior debt rate | B41: USD m | C41: =C39*Assumptions!$B$39 -> 0 | D41: =D39*Assumptions!$B$39 -> 2.7179068 | E41: =E39*Assumptions!$B$39 -> 2.5893521 | F41: =F39*Assumptions!$B$39 -> 2.4471703 | G41: =G39*Assumptions!$B$39 -> 2.2902478 | H41: =H39*Assumptions!$B$39 -> 2.1173825 | I41: =I39*Assumptions!$B$39 -> 1.9272765 | J41: =J39*Assumptions!$B$39 -> 1.7185285 | ... W41: =W39*Assumptions!$B$39 -> 0
A42: Scheduled debt service (sculpted) | B42: USD m | C42: =MIN(C10*$C$20,C39+C41) -> 0 | D42: =MIN(D10*$C$20,D39+D41) -> 3.7607308 | E42: =MIN(E10*$C$20,E39+E41) -> 3.7970648 | F42: =MIN(F10*$C$20,F39+F41) -> 3.8336531 | G42: =MIN(G10*$C$20,G39+G41) -> 3.8704907 | H42: =MIN(H10*$C$20,H39+H41) -> 3.9075724 | I42: =MIN(I10*$C$20,I39+I41) -> 3.9448926 | J42: =MIN(J10*$C$20,J39+J41) -> 3.9824453 | ... W42: =MIN(W10*$C$20,W39+W41) -> 0
A43: of which: scheduled principal | B43: USD m | C43: =C42-C41 -> 0 | D43: =D42-D41 -> 1.042824 | E43: =E42-E41 -> 1.2077127 | F43: =F42-F41 -> 1.3864828 | G43: =G42-G41 -> 1.5802429 | H43: =H42-H41 -> 1.7901899 | I43: =I42-I41 -> 2.0176161 | J43: =J42-J41 -> 2.2639169 | ... W43: =W42-W41 -> 0
A44: Cash sweep principal (50% of surplus cash) | B44: USD m | C44: =MIN(Assumptions!$B$44*Assumptions!$B$43*MAX(0,C8-C42),MAX(0,C39+C40-C43)) -> 0 | D44: =MIN(Assumptions!$B$44*Assumptions!$B$43*MAX(0,D8-D42),MAX(0,D39+D40-D43)) -> 0.56410962 | E44: =MIN(Assumptions!$B$44*Assumptions!$B$43*MAX(0,E8-E42),MAX(0,E39+E40-E43)) -> 0.56955972 | F44: =MIN(Assumptions!$B$44*Assumptions!$B$43*MAX(0,F8-F42),MAX(0,F39+F40-F43)) -> 0.57504796 | G44: =MIN(Assumptions!$B$44*Assumptions!$B$43*MAX(0,G8-G42),MAX(0,G39+G40-G43)) -> 0.5805736 | H44: =MIN(Assumptions!$B$44*Assumptions!$B$43*MAX(0,H8-H42),MAX(0,H39+H40-H43)) -> 0.58613586 | I44: =MIN(Assumptions!$B$44*Assumptions!$B$43*MAX(0,I8-I42),MAX(0,I39+I40-I43)) -> 0.59173389 | J44: =MIN(Assumptions!$B$44*Assumptions!$B$43*MAX(0,J8-J42),MAX(0,J39+J40-J43)) -> 0.5973668 | ... W44: =MIN(Assumptions!$B$44*Assumptions!$B$43*MAX(0,W8-W42),MAX(0,W39+W40-W43)) -> 0
A45: Total principal repaid | B45: USD m | C45: =C43+C44 -> 0 | D45: =D43+D44 -> 1.6069336 | E45: =E43+E44 -> 1.7772724 | F45: =F43+F44 -> 1.9615308 | G45: =G43+G44 -> 2.1608165 | H45: =H43+H44 -> 2.3763257 | I45: =I43+I44 -> 2.60935 | J45: =J43+J44 -> 2.8612837 | ... W45: =W43+W44 -> 0
A46: Closing balance | B46: USD m | C46: =C39+C40-C45 -> 33.973835 | D46: =D39+D40-D45 -> 32.366901 | E46: =E39+E40-E45 -> 30.589629 | F46: =F39+F40-F45 -> 28.628098 | G46: =G39+G40-G45 -> 26.467281 | H46: =H39+H40-H45 -> 24.090956 | I46: =I39+I40-I45 -> 21.481606 | J46: =J39+J40-J45 -> 18.620322 | ... W46: =W39+W40-W45 -> 0
A47: TOTAL DEBT SERVICE (interest + all principal) | B47: USD m | C47: =C41+C45 -> 0 | D47: =D41+D45 -> 4.3248404 | E47: =E41+E45 -> 4.3666245 | F47: =F41+F45 -> 4.4087011 | G47: =G41+G45 -> 4.4510643 | H47: =H41+H45 -> 4.4937083 | I47: =I41+I45 -> 4.5366265 | J47: =J41+J45 -> 4.5798121 | ... W47: =W41+W45 -> 0
A48: DSCR — scheduled debt service basis (covenant test) | B48: x | C48: =IF(C42<=0,0,C8/C42) -> 0 | D48: =IF(D42<=0,0,D8/D42) -> 1.3 | E48: =IF(E42<=0,0,E8/E42) -> 1.3 | F48: =IF(F42<=0,0,F8/F42) -> 1.3 | G48: =IF(G42<=0,0,G8/G42) -> 1.3 | H48: =IF(H42<=0,0,H8/H42) -> 1.3 | I48: =IF(I42<=0,0,I8/I42) -> 1.3 | J48: =IF(J42<=0,0,J8/J42) -> 1.3 | ... W48: =IF(W42<=0,0,W8/W42) -> 0
A49: DSCR — including cash sweep | B49: x | C49: =IF(C47<=0,0,C8/C47) -> 0 | D49: =IF(D47<=0,0,D8/D47) -> 1.1304348 | E49: =IF(E47<=0,0,E8/E47) -> 1.1304348 | F49: =IF(F47<=0,0,F8/F47) -> 1.1304348 | G49: =IF(G47<=0,0,G8/G47) -> 1.1304348 | H49: =IF(H47<=0,0,H8/H47) -> 1.1304348 | I49: =IF(I47<=0,0,I8/I47) -> 1.1304348 | J49: =IF(J47<=0,0,J8/J47) -> 1.1304348 | ... W49: =IF(W47<=0,0,W8/W47) -> 0
A50: Covenant check (scheduled DSCR >= minimum) | B50: flag | C50: =IF(C42<=0,"n/a",IF(C48>=Assumptions!$B$40-0.0001,"ok","BREACH")) -> n/a | D50: =IF(D42<=0,"n/a",IF(D48>=Assumptions!$B$40-0.0001,"ok","BREACH")) -> ok | E50: =IF(E42<=0,"n/a",IF(E48>=Assumptions!$B$40-0.0001,"ok","BREACH")) -> ok | F50: =IF(F42<=0,"n/a",IF(F48>=Assumptions!$B$40-0.0001,"ok","BREACH")) -> ok | G50: =IF(G42<=0,"n/a",IF(G48>=Assumptions!$B$40-0.0001,"ok","BREACH")) -> ok | H50: =IF(H42<=0,"n/a",IF(H48>=Assumptions!$B$40-0.0001,"ok","BREACH")) -> ok | I50: =IF(I42<=0,"n/a",IF(I48>=Assumptions!$B$40-0.0001,"ok","BREACH")) -> ok | J50: =IF(J42<=0,"n/a",IF(J48>=Assumptions!$B$40-0.0001,"ok","BREACH")) -> ok | ... W50: =IF(W42<=0,"n/a",IF(W48>=Assumptions!$B$40-0.0001,"ok","BREACH")) -> n/a
A52: 4. DEBT SERVICE RESERVE ACCOUNT
A53: DSRA required (6 months of forward scheduled debt service) | B53: USD m | C53: =Assumptions!$B$42/12*D42 -> 1.8803654 | D53: =Assumptions!$B$42/12*E42 -> 1.8985324 | E53: =Assumptions!$B$42/12*F42 -> 1.9168265 | F53: =Assumptions!$B$42/12*G42 -> 1.9352453 | G53: =Assumptions!$B$42/12*H42 -> 1.9537862 | H53: =Assumptions!$B$42/12*I42 -> 1.9724463 | I53: =Assumptions!$B$42/12*J42 -> 1.9912227 | J53: =Assumptions!$B$42/12*K42 -> 2.0101121 | ... W53: =Assumptions!$B$42/12*X42 -> 0
A54: Movement: (funding) / release | B54: USD m | C54: =-C53 -> -1.8803654 | D54: =C53-D53 -> -0.018167019 | E54: =D53-E53 -> -0.01829414 | F54: =E53-F53 -> -0.018418806 | G54: =F53-G53 -> -0.018540849 | H54: =G53-H53 -> -0.018660096 | I54: =H53-I53 -> -0.018776366 | J54: =I53-J53 -> -0.018889471 | K54: =J53-K53 -> -0.018999216 | ... W54: =V53-W53 -> 0
A55: DSRA closing balance | B55: USD m | C55: =C53 -> 1.8803654 | D55: =D53 -> 1.8985324 | E55: =E53 -> 1.9168265 | F55: =F53 -> 1.9352453 | G55: =G53 -> 1.9537862 | H55: =H53 -> 1.9724463 | I55: =I53 -> 1.9912227 | J55: =J53 -> 2.0101121 | ... W55: =W53 -> 0
A57: 5. EQUITY CASH FLOW & RETURNS
A58: CFADS | B58: USD m | C58: =C8 -> 0 | D58: =D8 -> 4.88895 | E58: =E8 -> 4.9361842 | F58: =F8 -> 4.983749 | G58: =G8 -> 5.0316379 | H58: =H8 -> 5.0798441 | I58: =I8 -> 5.1283604 | J58: =J8 -> 5.1771789 | ... W58: =W8 -> 5.8348337
A59: Less: total debt service | B59: USD m | C59: =-C47 -> 0 | D59: =-D47 -> -4.3248404 | E59: =-E47 -> -4.3666245 | F59: =-F47 -> -4.4087011 | G59: =-G47 -> -4.4510643 | H59: =-H47 -> -4.4937083 | I59: =-I47 -> -4.5366265 | J59: =-J47 -> -4.5798121 | ... W59: =-W47 -> 0
A60: Add: interest tax shield (capped at taxable profit) | B60: USD m | C60: =MAX(0,MIN(C41,Model!C26))*Assumptions!$B$33 -> 0 | D60: =MAX(0,MIN(D41,Model!D26))*Assumptions!$B$33 -> 0.80955 | E60: =MAX(0,MIN(E41,Model!E26))*Assumptions!$B$33 -> 0.77680563 | F60: =MAX(0,MIN(F41,Model!F26))*Assumptions!$B$33 -> 0.73415109 | G60: =MAX(0,MIN(G41,Model!G26))*Assumptions!$B$33 -> 0.68707435 | H60: =MAX(0,MIN(H41,Model!H26))*Assumptions!$B$33 -> 0.63521476 | I60: =MAX(0,MIN(I41,Model!I26))*Assumptions!$B$33 -> 0.57818294 | J60: =MAX(0,MIN(J41,Model!J26))*Assumptions!$B$33 -> 0.51555854 | ... W60: =MAX(0,MIN(W41,Model!W26))*Assumptions!$B$33 -> 0
A61: DSRA: (funding) / release | B61: USD m | C61: =C54 -> -1.8803654 | D61: =D54 -> -0.018167019 | E61: =E54 -> -0.01829414 | F61: =F54 -> -0.018418806 | G61: =G54 -> -0.018540849 | H61: =H54 -> -0.018660096 | I61: =I54 -> -0.018776366 | J61: =J54 -> -0.018889471 | ... W61: =W54 -> 0
A62: Less: sponsor equity injection into capex | B62: USD m | C62: =-IF(C4=0,Assumptions!$B$15-$C$17,0) -> -26.026165 | D62: =-IF(D4=0,Assumptions!$B$15-$C$17,0) -> 0 | E62: =-IF(E4=0,Assumptions!$B$15-$C$17,0) -> 0 | F62: =-IF(F4=0,Assumptions!$B$15-$C$17,0) -> 0 | G62: =-IF(G4=0,Assumptions!$B$15-$C$17,0) -> 0 | H62: =-IF(H4=0,Assumptions!$B$15-$C$17,0) -> 0 | I62: =-IF(I4=0,Assumptions!$B$15-$C$17,0) -> 0 | J62: =-IF(J4=0,Assumptions!$B$15-$C$17,0) -> 0 | ... W62: =-IF(W4=0,Assumptions!$B$15-$C$17,0) -> 0
A63: EQUITY CASH FLOW | B63: USD m | C63: =SUM(C58:C62) -> -27.906531 | D63: =SUM(D58:D62) -> 1.3554926 | E63: =SUM(E58:E62) -> 1.3280712 | F63: =SUM(F58:F62) -> 1.2907802 | G63: =SUM(G58:G62) -> 1.2491071 | H63: =SUM(H58:H62) -> 1.2026905 | I63: =SUM(I58:I62) -> 1.1511405 | J63: =SUM(J58:J62) -> 1.0940359 | ... W63: =SUM(W58:W62) -> 5.8348337
A64: Cumulative equity cash flow | B64: USD m | C64: =C63 -> -27.906531 | D64: =C64+D63 -> -26.551038 | E64: =D64+E63 -> -25.222967 | F64: =E64+F63 -> -23.932187 | G64: =F64+G63 -> -22.683079 | H64: =G64+H63 -> -21.480389 | I64: =H64+I63 -> -20.329248 | J64: =I64+J63 -> -19.235213 | K64: =J64+K63 -> -18.20429 | ... W64: =V64+W63 -> 32.733361
A66: Levered returns & covenant summary | C66: Value
A67: EQUITY IRR (post-tax, nominal USD) | B67: % | C67: =IRR(C63:W63) -> 0.060358843
A68: Project IRR (unlevered, from Model tab) | B68: % | C68: =Model!$C$43 -> 0.060665745
A69: MINIMUM DSCR across the debt tenor | B69: x | C69: {=MIDIFS(C48:W48,C48:W48,">0")} -> #NAME?
A70: AVERAGE DSCR across the debt tenor | B70: x | C70: =AVERAGEIF(C48:W48,">0") -> 1.3
A71: Minimum DSCR including the cash sweep | B71: x | C71: {=MIDIFS(C49:W49,C49:W49,">0")} -> #NAME?
A72: Debt fully repaid in operating year | B72: year | C72: =IF(W46>0.001,"Not repaid",COUNTIF(C46:W46,">0.001")) -> 12
A73: Years ahead of the 15-year tenor | B73: years | C73: =Assumptions!$B$38-C72 -> 3
A74: Equity cash-on-cash multiple | B74: x | C74: =SUM(D63:W63)/-C63 -> 2.1729642
A75: Equity payback (operating years from COD) | B75: years | C75: =IF(W64<0,"Not repaid",COUNTIF(D64:W64,"<0")+1) -> 15
A76: Check: no DSCR covenant breach in any period | B76: flag | C76: =IF(COUNTIF(C50:W50,"BREACH")=0,"ok","BREACH") -> ok
A77: Check: closing debt balance is nil at end of tenor | B77: flag | C77: =IF(ABS(W46)<0.001,"ok","CHECK") -> ok
A78: Note: the DSCR covenant is tested against scheduled debt service. The cash sweep is a mandatory prepayment of surplus cash that sits below the covenant test — market-standard treatment.
A80: 6. WHY WE CHOSE A SCULPTED REPAYMENT PROFILE OVER LEVEL DEBT SERVICE
A81: The DIF term sheet permits either. We have sculpted to a target DSCR of 1.30x for three reasons.
A82: First, it maximises debt capacity for a given covenant. Sculpting sets each period's debt service as a fixed multiple of that period's CFADS, so every year contributes its full affordable amount. A level-annuity profile must be sized to the WORST year's coverage, which on an escalating revenue line is Year 1 — the constraint then binds for fifteen years even though CFADS grows throughout. On these numbers sculpting supports USD 33.97m; a level profile sized to keep Year 1 at 1.30x would support materially less and would leave the sponsor to fund the difference in equity that earns below its cost.
A83: Second, it matches the cash flow shape of the asset. A solar IPP under a take-or-pay PPA has near-deterministic revenue that escalates at a contractual 1.5% while opex escalates at 3%, so CFADS rises gently and predictably from USD 4.89m to USD 5.83m. Sculpting tracks that curve. Level debt service deliberately mismatches it: coverage is tightest exactly when the plant is newest, least proven and most exposed to commissioning and early-life performance risk — which is the wrong way round from a credit perspective.
A84: Third, it gives the credit committee a flat, legible covenant profile. Scheduled DSCR is 1.30x in every one of the twelve repayment periods — minimum equals average equals target. There is no single weak year to argue about, no back-ended balloon, and the covenant test is trivially auditable. Under a level profile DSCR would drift upward over time, which looks reassuring in later years but concentrates all of the risk in the early ones.
A85: The honest trade-off against sculpting: it leaves zero headroom by construction. Because debt service is set at exactly CFADS divided by 1.30, any CFADS underperformance breaches the covenant immediately — there is no cushion absorbing a bad year. This is why our first recommended mitigant is to sculpt to 1.40x or 1.45x instead, accepting a smaller facility in exchange for real headroom. Change the target DSCR input on the Assumptions tab and the entire schedule, sizing and equity IRR resize accordingly.
A86: A level-annuity alternative can be produced from this model by replacing the scheduled debt service row with =PMT(interest rate, remaining tenor, -opening balance); we have not hard-wired a toggle because the sculpted case is the one we would take to committee.
A88: 7. WHY LEVERAGE IS ROUGHLY VALUE-NEUTRAL — DECOMPOSITION | C88: Value
A89: Total interest paid over the life of the facility | B89: USD m | C89: =SUM(C41:W41) -> 20.503907
A90: Total interest tax shield captured | B90: USD m | C90: =SUM(C60:W60) -> 6.14535
A91: Shield as % of interest (approaches the tax rate) | B91: % | C91: =C90/C89 -> 0.29971605
A92: Effective AFTER-TAX cost of the DIF senior debt | B92: % | C92: =Assumptions!$B$39*(1-C91) -> 0.056022716
A93: Project (unlevered) IRR — the asset return | B93: % | C93: =Model!$C$43 -> 0.060665745
A94: SPREAD: asset return less after-tax cost of debt | B94: pp | C94: =(C93-C92)*100 -> 0.4643029
A95: Equity IRR actually achieved | B95: % | C95: =C67 -> 0.060358843
A96: Net effect of leverage on equity IRR | B96: pp | C96: =(C95-C93)*100 -> -0.030690223
A97: DSRA funded at COD and idle until release | B97: USD m | C97: =C53 -> 1.8803654
A98: Years the DSRA is tied up earning nothing | B98: years | C98: =C72 -> 12
A99: The naive read is that an 8.0% coupon against a 6.07% asset return must dilute equity. That is wrong, and the decomposition above shows why: interest is tax-deductible, so the shield of USD 6.15m recovers almost exactly the 30% tax rate and drops the effective cost of the facility to 5.60% — roughly 47bp BELOW the unlevered asset return. On a pure cost-of-capital basis this leverage is marginally accretive.
A100: The reason equity IRR still lands 3bp below the project IRR is not the coupon at all. It is the debt service reserve account: USD 1.88m of sponsor equity is locked at COD, earns nothing for twelve years, and is only returned when the facility is retired. That idle capital costs the equity holder more than the thin positive spread on the debt earns. Net effect: leverage here is value-neutral to three basis points, which is a materially different conclusion from 'the debt is too expensive'.
A101: The conclusion that matters is unchanged and should lead the deck: BOTH returns are approximately 6% in nominal USD. The problem is not the capital structure, which is efficient and well covenanted. The problem is the asset economics — a 0.075/kWh tariff against 60m of capex. No financing structure can fix a project whose unlevered return is 4pp below its own discount rate; only the tariff or the capital cost can.

Sheet Sensitivities
A1: SENSITIVITY ANALYSIS — PROJECT RETURNS
A2: Grids are driven by the live scenario engine lower down this tab — every number traces to a visible formula. Base case sits in the centre cell (highlighted).
A4: Tariff step size | B4: 0.005 | C4: USD / kWh
A5: Capacity factor step size | B5: 0.015 | C5: percentage points
A6: Capex step size | B6: 5 | C6: USD m
A9: GRID 1 — PROJECT (UNLEVERED) IRR: NET CAPACITY FACTOR vs PPA TARIFF | K9: GRID 3 — PROJECT (UNLEVERED) IRR: TOTAL CAPEX vs NET CAPACITY FACTOR
C10: PPA tariff (USD / kWh) → | M10: Total capex (USD m) →
B11: Project IRR | C11: =Assumptions!$B$23-3*$B$4 -> 0.06 | D11: =C11+$B$4 -> 0.065 | E11: =D11+$B$4 -> 0.07 | F11: =E11+$B$4 -> 0.075 | G11: =F11+$B$4 -> 0.08 | H11: =G11+$B$4 -> 0.085 | I11: =H11+$B$4 -> 0.09 | L11: Project IRR | M11: =Assumptions!$B$15-3*$B$6 -> 45 | N11: =M11+$B$6 -> 50 | O11: =N11+$B$6 -> 55 | P11: =O11+$B$6 -> 60 | Q11: =P11+$B$6 -> 65 | R11: =Q11+$B$6 -> 70 | S11: =R11+$B$6 -> 75
A12: Net capacity factor ↓ | B12: =Assumptions!$B$9-3*$B$5 -> 0.165 | C12: {=INDEX($E$41:$E$89,(ROW()-ROW($B$12))*7+(COLUMN()-COLUMN($B$12)))} -> 0.0085171816 | D12: {=INDEX($E$41:$E$89,(ROW()-ROW($B$12))*7+(COLUMN()-COLUMN($B$12)))} -> 0.016893192 | E12: {=INDEX($E$41:$E$89,(ROW()-ROW($B$12))*7+(COLUMN()-COLUMN($B$12)))} -> 0.024845974 | F12: {=INDEX($E$41:$E$89,(ROW()-ROW($B$12))*7+(COLUMN()-COLUMN($B$12)))} -> 0.03243855 | G12: {=INDEX($E$41:$E$89,(ROW()-ROW($B$12))*7+(COLUMN()-COLUMN($B$12)))} -> 0.039721017 | H12: {=INDEX($E$41:$E$89,(ROW()-ROW($B$12))*7+(COLUMN()-COLUMN($B$12)))} -> 0.046733887 | I12: {=INDEX($E$41:$E$89,(ROW()-ROW($B$12))*7+(COLUMN()-COLUMN($B$12)))} -> 0.053510401 | K12: Capacity factor ↓ | L12: =$B12 -> 0.165 | M12: {=INDEX($F$92:$F$140,(ROW()-ROW($L$12))*7+(COLUMN()-COLUMN($L$12)))} -> 0.058445397 | N12: {=INDEX($F$92:$F$140,(ROW()-ROW($L$12))*7+(COLUMN()-COLUMN($L$12)))} -> 0.048419863 | O12: {=INDEX($F$92:$F$140,(ROW()-ROW($L$12))*7+(COLUMN()-COLUMN($L$12)))} -> 0.039859706 | P12: {=INDEX($F$92:$F$140,(ROW()-ROW($L$12))*7+(COLUMN()-COLUMN($L$12)))} -> 0.03243855 | Q12: {=INDEX($F$92:$F$140,(ROW()-ROW($L$12))*7+(COLUMN()-COLUMN($L$12)))} -> 0.025924153 | R12: {=INDEX($F$92:$F$140,(ROW()-ROW($L$12))*7+(COLUMN()-COLUMN($L$12)))} -> 0.020146043 | S12: {=INDEX($F$92:$F$140,(ROW()-ROW($L$12))*7+(COLUMN()-COLUMN($L$12)))} -> 0.014975799
B13: =B12+$B$5 -> 0.18 | C13: {=INDEX($E$41:$E$89,(ROW()-ROW($B$12))*7+(COLUMN()-COLUMN($B$12)))} -> 0.017632604 | D13: {=INDEX($E$41:$E$89,(ROW()-ROW($B$12))*7+(COLUMN()-COLUMN($B$12)))} -> 0.026251618 | E13: {=INDEX($E$41:$E$89,(ROW()-ROW($B$12))*7+(COLUMN()-COLUMN($B$12)))} -> 0.034453576 | F13: {=INDEX($E$41:$E$89,(ROW()-ROW($B$12))*7+(COLUMN()-COLUMN($B$12)))} -> 0.042300459 | G13: {=INDEX($E$41:$E$89,(ROW()-ROW($B$12))*7+(COLUMN()-COLUMN($B$12)))} -> 0.049841645 | H13: {=INDEX($E$41:$E$89,(ROW()-ROW($B$12))*7+(COLUMN()-COLUMN($B$12)))} -> 0.057117133 | I13: {=INDEX($E$41:$E$89,(ROW()-ROW($B$12))*7+(COLUMN()-COLUMN($B$12)))} -> 0.064159798 | L13: =$B13 -> 0.18 | M13: {=INDEX($F$92:$F$140,(ROW()-ROW($L$12))*7+(COLUMN()-COLUMN($L$12)))} -> 0.070042992 | N13: {=INDEX($F$92:$F$140,(ROW()-ROW($L$12))*7+(COLUMN()-COLUMN($L$12)))} -> 0.059338123 | O13: {=INDEX($F$92:$F$140,(ROW()-ROW($L$12))*7+(COLUMN()-COLUMN($L$12)))} -> 0.050208597 | P13: {=INDEX($F$92:$F$140,(ROW()-ROW($L$12))*7+(COLUMN()-COLUMN($L$12)))} -> 0.042300459 | Q13: {=INDEX($F$92:$F$140,(ROW()-ROW($L$12))*7+(COLUMN()-COLUMN($L$12)))} -> 0.03536263 | R13: {=INDEX($F$92:$F$140,(ROW()-ROW($L$12))*7+(COLUMN()-COLUMN($L$12)))} -> 0.029211304 | S13: {=INDEX($F$92:$F$140,(ROW()-ROW($L$12))*7+(COLUMN()-COLUMN($L$12)))} -> 0.023708352
B14: =B13+$B$5 -> 0.195 | C14: {=INDEX($E$41:$E$89,(ROW()-ROW($B$12))*7+(COLUMN()-COLUMN($B$12)))} -> 0.026251618 | D14: {=INDEX($E$41:$E$89,(ROW()-ROW($B$12))*7+(COLUMN()-COLUMN($B$12)))} -> 0.035120291 | E14: {=INDEX($E$41:$E$89,(ROW()-ROW($B$12))*7+(COLUMN()-COLUMN($B$12)))} -> 0.043577371 | F14: {=INDEX($E$41:$E$89,(ROW()-ROW($B$12))*7+(COLUMN()-COLUMN($B$12)))} -> 0.051684035 | G14: {=INDEX($E$41:$E$89,(ROW()-ROW($B$12))*7+(COLUMN()-COLUMN($B$12)))} -> 0.059489106 | H14: {=INDEX($E$41:$E$89,(ROW()-ROW($B$12))*7+(COLUMN()-COLUMN($B$12)))} -> 0.067032192 | I14: {=INDEX($E$41:$E$89,(ROW()-ROW($B$12))*7+(COLUMN()-COLUMN($B$12)))} -> 0.074345885 | L14: =$B14 -> 0.195 | M14: {=INDEX($F$92:$F$140,(ROW()-ROW($L$12))*7+(COLUMN()-COLUMN($L$12)))} -> 0.081117303 | N14: {=INDEX($F$92:$F$140,(ROW()-ROW($L$12))*7+(COLUMN()-COLUMN($L$12)))} -> 0.069747715 | O14: {=INDEX($F$92:$F$140,(ROW()-ROW($L$12))*7+(COLUMN()-COLUMN($L$12)))} -> 0.060063966 | P14: {=INDEX($F$92:$F$140,(ROW()-ROW($L$12))*7+(COLUMN()-COLUMN($L$12)))} -> 0.051684035 | Q14: {=INDEX($F$92:$F$140,(ROW()-ROW($L$12))*7+(COLUMN()-COLUMN($L$12)))} -> 0.04433772 | R14: {=INDEX($F$92:$F$140,(ROW()-ROW($L$12))*7+(COLUMN()-COLUMN($L$12)))} -> 0.037827732 | S14: {=INDEX($F$92:$F$140,(ROW()-ROW($L$12))*7+(COLUMN()-COLUMN($L$12)))} -> 0.032006142
B15: =B14+$B$5 -> 0.21 | C15: {=INDEX($E$41:$E$89,(ROW()-ROW($B$12))*7+(COLUMN()-COLUMN($B$12)))} -> 0.034453576 | D15: {=INDEX($E$41:$E$89,(ROW()-ROW($B$12))*7+(COLUMN()-COLUMN($B$12)))} -> 0.043577371 | E15: {=INDEX($E$41:$E$89,(ROW()-ROW($B$12))*7+(COLUMN()-COLUMN($B$12)))} -> 0.052294578 | F15: {=INDEX($E$41:$E$89,(ROW()-ROW($B$12))*7+(COLUMN()-COLUMN($B$12)))} -> 0.060665745 | G15: {=INDEX($E$41:$E$89,(ROW()-ROW($B$12))*7+(COLUMN()-COLUMN($B$12)))} -> 0.068739261 | H15: {=INDEX($E$41:$E$89,(ROW()-ROW($B$12))*7+(COLUMN()-COLUMN($B$12)))} -> 0.076554428 | I15: {=INDEX($E$41:$E$89,(ROW()-ROW($B$12))*7+(COLUMN()-COLUMN($B$12)))} -> 0.084143615 | L15: =$B15 -> 0.21 | M15: {=INDEX($F$92:$F$140,(ROW()-ROW($L$12))*7+(COLUMN()-COLUMN($L$12)))} -> 0.091758396 | N15: {=INDEX($F$92:$F$140,(ROW()-ROW($L$12))*7+(COLUMN()-COLUMN($L$12)))} -> 0.079733801 | O15: {=INDEX($F$92:$F$140,(ROW()-ROW($L$12))*7+(COLUMN()-COLUMN($L$12)))} -> 0.069506456 | P15: {=INDEX($F$92:$F$140,(ROW()-ROW($L$12))*7+(COLUMN()-COLUMN($L$12)))} -> 0.060665745 | Q15: {=INDEX($F$92:$F$140,(ROW()-ROW($L$12))*7+(COLUMN()-COLUMN($L$12)))} -> 0.052922032 | R15: {=INDEX($F$92:$F$140,(ROW()-ROW($L$12))*7+(COLUMN()-COLUMN($L$12)))} -> 0.046064353 | S15: {=INDEX($F$92:$F$140,(ROW()-ROW($L$12))*7+(COLUMN()-COLUMN($L$12)))} -> 0.039934868
B16: =B15+$B$5 -> 0.225 | C16: {=INDEX($E$41:$E$89,(ROW()-ROW($B$12))*7+(COLUMN()-COLUMN($B$12)))} -> 0.042300459 | D16: {=INDEX($E$41:$E$89,(ROW()-ROW($B$12))*7+(COLUMN()-COLUMN($B$12)))} -> 0.051684035 | E16: {=INDEX($E$41:$E$89,(ROW()-ROW($B$12))*7+(COLUMN()-COLUMN($B$12)))} -> 0.060665745 | F16: {=INDEX($E$41:$E$89,(ROW()-ROW($B$12))*7+(COLUMN()-COLUMN($B$12)))} -> 0.069305636 | G16: {=INDEX($E$41:$E$89,(ROW()-ROW($B$12))*7+(COLUMN()-COLUMN($B$12)))} -> 0.077651751 | H16: {=INDEX($E$41:$E$89,(ROW()-ROW($B$12))*7+(COLUMN()-COLUMN($B$12)))} -> 0.085743147 | I16: {=INDEX($E$41:$E$89,(ROW()-ROW($B$12))*7+(COLUMN()-COLUMN($B$12)))} -> 0.093612013 | L16: =$B16 -> 0.225 | M16: {=INDEX($F$92:$F$140,(ROW()-ROW($L$12))*7+(COLUMN()-COLUMN($L$12)))} -> 0.10203618 | N16: {=INDEX($F$92:$F$140,(ROW()-ROW($L$12))*7+(COLUMN()-COLUMN($L$12)))} -> 0.089362756 | O16: {=INDEX($F$92:$F$140,(ROW()-ROW($L$12))*7+(COLUMN()-COLUMN($L$12)))} -> 0.078599161 | P16: {=INDEX($F$92:$F$140,(ROW()-ROW($L$12))*7+(COLUMN()-COLUMN($L$12)))} -> 0.069305636 | Q16: {=INDEX($F$92:$F$140,(ROW()-ROW($L$12))*7+(COLUMN()-COLUMN($L$12)))} -> 0.061172778 | R16: {=INDEX($F$92:$F$140,(ROW()-ROW($L$12))*7+(COLUMN()-COLUMN($L$12)))} -> 0.05397574 | S16: {=INDEX($F$92:$F$140,(ROW()-ROW($L$12))*7+(COLUMN()-COLUMN($L$12)))} -> 0.047546642
B17: =B16+$B$5 -> 0.24 | C17: {=INDEX($E$41:$E$89,(ROW()-ROW($B$12))*7+(COLUMN()-COLUMN($B$12)))} -> 0.049841645 | D17: {=INDEX($E$41:$E$89,(ROW()-ROW($B$12))*7+(COLUMN()-COLUMN($B$12)))} -> 0.059489106 | E17: {=INDEX($E$41:$E$89,(ROW()-ROW($B$12))*7+(COLUMN()-COLUMN($B$12)))} -> 0.068739261 | F17: {=INDEX($E$41:$E$89,(ROW()-ROW($B$12))*7+(COLUMN()-COLUMN($B$12)))} -> 0.077651751 | G17: {=INDEX($E$41:$E$89,(ROW()-ROW($B$12))*7+(COLUMN()-COLUMN($B$12)))} -> 0.086274338 | H17: {=INDEX($E$41:$E$89,(ROW()-ROW($B$12))*7+(COLUMN()-COLUMN($B$12)))} -> 0.094645877 | I17: {=INDEX($E$41:$E$89,(ROW()-ROW($B$12))*7+(COLUMN()-COLUMN($B$12)))} -> 0.10279841 | L17: =$B17 -> 0.24 | M17: {=INDEX($F$92:$F$140,(ROW()-ROW($L$12))*7+(COLUMN()-COLUMN($L$12)))} -> 0.112006 | N17: {=INDEX($F$92:$F$140,(ROW()-ROW($L$12))*7+(COLUMN()-COLUMN($L$12)))} -> 0.098687336 | O17: {=INDEX($F$92:$F$140,(ROW()-ROW($L$12))*7+(COLUMN()-COLUMN($L$12)))} -> 0.087392401 | P17: {=INDEX($F$92:$F$140,(ROW()-ROW($L$12))*7+(COLUMN()-COLUMN($L$12)))} -> 0.077651751 | Q17: {=INDEX($F$92:$F$140,(ROW()-ROW($L$12))*7+(COLUMN()-COLUMN($L$12)))} -> 0.069135873 | R17: {=INDEX($F$92:$F$140,(ROW()-ROW($L$12))*7+(COLUMN()-COLUMN($L$12)))} -> 0.061605818 | S17: {=INDEX($F$92:$F$140,(ROW()-ROW($L$12))*7+(COLUMN()-COLUMN($L$12)))} -> 0.054883522
B18: =B17+$B$5 -> 0.255 | C18: {=INDEX($E$41:$E$89,(ROW()-ROW($B$12))*7+(COLUMN()-COLUMN($B$12)))} -> 0.057117133 | D18: {=INDEX($E$41:$E$89,(ROW()-ROW($B$12))*7+(COLUMN()-COLUMN($B$12)))} -> 0.067032192 | E18: {=INDEX($E$41:$E$89,(ROW()-ROW($B$12))*7+(COLUMN()-COLUMN($B$12)))} -> 0.076554428 | F18: {=INDEX($E$41:$E$89,(ROW()-ROW($B$12))*7+(COLUMN()-COLUMN($B$12)))} -> 0.085743147 | G18: {=INDEX($E$41:$E$89,(ROW()-ROW($B$12))*7+(COLUMN()-COLUMN($B$12)))} -> 0.094645877 | H18: {=INDEX($E$41:$E$89,(ROW()-ROW($B$12))*7+(COLUMN()-COLUMN($B$12)))} -> 0.1033013 | I18: {=INDEX($E$41:$E$89,(ROW()-ROW($B$12))*7+(COLUMN()-COLUMN($B$12)))} -> 0.11174133 | L18: =$B18 -> 0.255 | M18: {=INDEX($F$92:$F$140,(ROW()-ROW($L$12))*7+(COLUMN()-COLUMN($L$12)))} -> 0.12171244 | N18: {=INDEX($F$92:$F$140,(ROW()-ROW($L$12))*7+(COLUMN()-COLUMN($L$12)))} -> 0.10775017 | O18: {=INDEX($F$92:$F$140,(ROW()-ROW($L$12))*7+(COLUMN()-COLUMN($L$12)))} -> 0.095926966 | P18: {=INDEX($F$92:$F$140,(ROW()-ROW($L$12))*7+(COLUMN()-COLUMN($L$12)))} -> 0.085743147 | Q18: {=INDEX($F$92:$F$140,(ROW()-ROW($L$12))*7+(COLUMN()-COLUMN($L$12)))} -> 0.076848745 | R18: {=INDEX($F$92:$F$140,(ROW()-ROW($L$12))*7+(COLUMN()-COLUMN($L$12)))} -> 0.068990481 | S18: {=INDEX($F$92:$F$140,(ROW()-ROW($L$12))*7+(COLUMN()-COLUMN($L$12)))} -> 0.061979964
A21: GRID 2 — PROJECT NPV AT 10% DISCOUNT RATE (USD m): CAPACITY FACTOR vs PPA TARIFF
C22: PPA tariff (USD / kWh) →
B23: NPV (USD m) | C23: =C$11 -> 0.06 | D23: =D$11 -> 0.065 | E23: =E$11 -> 0.07 | F23: =F$11 -> 0.075 | G23: =G$11 -> 0.08 | H23: =H$11 -> 0.085 | I23: =I$11 -> 0.09
A24: Net capacity factor ↓ | B24: =$B12 -> 0.165 | C24: {=INDEX($F$41:$F$89,(ROW()-ROW($B$24))*7+(COLUMN()-COLUMN($B$24)))} -> -32.555476 | D24: {=INDEX($F$41:$F$89,(ROW()-ROW($B$24))*7+(COLUMN()-COLUMN($B$24)))} -> -30.175417 | E24: {=INDEX($F$41:$F$89,(ROW()-ROW($B$24))*7+(COLUMN()-COLUMN($B$24)))} -> -27.795357 | F24: {=INDEX($F$41:$F$89,(ROW()-ROW($B$24))*7+(COLUMN()-COLUMN($B$24)))} -> -25.415298 | G24: {=INDEX($F$41:$F$89,(ROW()-ROW($B$24))*7+(COLUMN()-COLUMN($B$24)))} -> -23.035238 | H24: {=INDEX($F$41:$F$89,(ROW()-ROW($B$24))*7+(COLUMN()-COLUMN($B$24)))} -> -20.655179 | I24: {=INDEX($F$41:$F$89,(ROW()-ROW($B$24))*7+(COLUMN()-COLUMN($B$24)))} -> -18.275119
B25: =$B13 -> 0.18 | C25: {=INDEX($F$41:$F$89,(ROW()-ROW($B$24))*7+(COLUMN()-COLUMN($B$24)))} -> -29.959048 | D25: {=INDEX($F$41:$F$89,(ROW()-ROW($B$24))*7+(COLUMN()-COLUMN($B$24)))} -> -27.362619 | E25: {=INDEX($F$41:$F$89,(ROW()-ROW($B$24))*7+(COLUMN()-COLUMN($B$24)))} -> -24.766191 | F25: {=INDEX($F$41:$F$89,(ROW()-ROW($B$24))*7+(COLUMN()-COLUMN($B$24)))} -> -22.169762 | G25: {=INDEX($F$41:$F$89,(ROW()-ROW($B$24))*7+(COLUMN()-COLUMN($B$24)))} -> -19.573334 | H25: {=INDEX($F$41:$F$89,(ROW()-ROW($B$24))*7+(COLUMN()-COLUMN($B$24)))} -> -16.976905 | I25: {=INDEX($F$41:$F$89,(ROW()-ROW($B$24))*7+(COLUMN()-COLUMN($B$24)))} -> -14.380477
B26: =$B14 -> 0.195 | C26: {=INDEX($F$41:$F$89,(ROW()-ROW($B$24))*7+(COLUMN()-COLUMN($B$24)))} -> -27.362619 | D26: {=INDEX($F$41:$F$89,(ROW()-ROW($B$24))*7+(COLUMN()-COLUMN($B$24)))} -> -24.549822 | E26: {=INDEX($F$41:$F$89,(ROW()-ROW($B$24))*7+(COLUMN()-COLUMN($B$24)))} -> -21.737024 | F26: {=INDEX($F$41:$F$89,(ROW()-ROW($B$24))*7+(COLUMN()-COLUMN($B$24)))} -> -18.924227 | G26: {=INDEX($F$41:$F$89,(ROW()-ROW($B$24))*7+(COLUMN()-COLUMN($B$24)))} -> -16.111429 | H26: {=INDEX($F$41:$F$89,(ROW()-ROW($B$24))*7+(COLUMN()-COLUMN($B$24)))} -> -13.298632 | I26: {=INDEX($F$41:$F$89,(ROW()-ROW($B$24))*7+(COLUMN()-COLUMN($B$24)))} -> -10.485834
B27: =$B15 -> 0.21 | C27: {=INDEX($F$41:$F$89,(ROW()-ROW($B$24))*7+(COLUMN()-COLUMN($B$24)))} -> -24.766191 | D27: {=INDEX($F$41:$F$89,(ROW()-ROW($B$24))*7+(COLUMN()-COLUMN($B$24)))} -> -21.737024 | E27: {=INDEX($F$41:$F$89,(ROW()-ROW($B$24))*7+(COLUMN()-COLUMN($B$24)))} -> -18.707858 | F27: {=INDEX($F$41:$F$89,(ROW()-ROW($B$24))*7+(COLUMN()-COLUMN($B$24)))} -> -15.678691 | G27: {=INDEX($F$41:$F$89,(ROW()-ROW($B$24))*7+(COLUMN()-COLUMN($B$24)))} -> -12.649524 | H27: {=INDEX($F$41:$F$89,(ROW()-ROW($B$24))*7+(COLUMN()-COLUMN($B$24)))} -> -9.6203578 | I27: {=INDEX($F$41:$F$89,(ROW()-ROW($B$24))*7+(COLUMN()-COLUMN($B$24)))} -> -6.5911912
B28: =$B16 -> 0.225 | C28: {=INDEX($F$41:$F$89,(ROW()-ROW($B$24))*7+(COLUMN()-COLUMN($B$24)))} -> -22.169762 | D28: {=INDEX($F$41:$F$89,(ROW()-ROW($B$24))*7+(COLUMN()-COLUMN($B$24)))} -> -18.924227 | E28: {=INDEX($F$41:$F$89,(ROW()-ROW($B$24))*7+(COLUMN()-COLUMN($B$24)))} -> -15.678691 | F28: {=INDEX($F$41:$F$89,(ROW()-ROW($B$24))*7+(COLUMN()-COLUMN($B$24)))} -> -12.433155 | G28: {=INDEX($F$41:$F$89,(ROW()-ROW($B$24))*7+(COLUMN()-COLUMN($B$24)))} -> -9.1876197 | H28: {=INDEX($F$41:$F$89,(ROW()-ROW($B$24))*7+(COLUMN()-COLUMN($B$24)))} -> -5.9420841 | I28: {=INDEX($F$41:$F$89,(ROW()-ROW($B$24))*7+(COLUMN()-COLUMN($B$24)))} -> -2.6965485
B29: =$B17 -> 0.24 | C29: {=INDEX($F$41:$F$89,(ROW()-ROW($B$24))*7+(COLUMN()-COLUMN($B$24)))} -> -19.573334 | D29: {=INDEX($F$41:$F$89,(ROW()-ROW($B$24))*7+(COLUMN()-COLUMN($B$24)))} -> -16.111429 | E29: {=INDEX($F$41:$F$89,(ROW()-ROW($B$24))*7+(COLUMN()-COLUMN($B$24)))} -> -12.649524 | F29: {=INDEX($F$41:$F$89,(ROW()-ROW($B$24))*7+(COLUMN()-COLUMN($B$24)))} -> -9.1876197 | G29: {=INDEX($F$41:$F$89,(ROW()-ROW($B$24))*7+(COLUMN()-COLUMN($B$24)))} -> -5.7257151 | H29: {=INDEX($F$41:$F$89,(ROW()-ROW($B$24))*7+(COLUMN()-COLUMN($B$24)))} -> -2.2638104 | I29: {=INDEX($F$41:$F$89,(ROW()-ROW($B$24))*7+(COLUMN()-COLUMN($B$24)))} -> 1.1980942
B30: =$B18 -> 0.255 | C30: {=INDEX($F$41:$F$89,(ROW()-ROW($B$24))*7+(COLUMN()-COLUMN($B$24)))} -> -16.976905 | D30: {=INDEX($F$41:$F$89,(ROW()-ROW($B$24))*7+(COLUMN()-COLUMN($B$24)))} -> -13.298632 | E30: {=INDEX($F$41:$F$89,(ROW()-ROW($B$24))*7+(COLUMN()-COLUMN($B$24)))} -> -9.6203578 | F30: {=INDEX($F$41:$F$89,(ROW()-ROW($B$24))*7+(COLUMN()-COLUMN($B$24)))} -> -5.9420841 | G30: {=INDEX($F$41:$F$89,(ROW()-ROW($B$24))*7+(COLUMN()-COLUMN($B$24)))} -> -2.2638104 | H30: {=INDEX($F$41:$F$89,(ROW()-ROW($B$24))*7+(COLUMN()-COLUMN($B$24)))} -> 1.4144633 | I30: {=INDEX($F$41:$F$89,(ROW()-ROW($B$24))*7+(COLUMN()-COLUMN($B$24)))} -> 5.092737
A31: Base case is outlined in red. The scenario engine rows below (grouped — click + to expand) contain the full 21-year cash flow for each of the 98 scenarios; the grids simply INDEX into them, so no static values are used anywhere.
A32: ▼ SCENARIO ENGINE (grouped — expand to audit)
A33: SCENARIO ENGINE — SHARED YEAR-BY-YEAR DRIVERS (identical across all scenarios)
G34: Year → | H34: 0 | I34: =H34+1 -> 1 | J34: =I34+1 -> 2 | K34: =J34+1 -> 3 | L34: =K34+1 -> 4 | M34: =L34+1 -> 5 | N34: =M34+1 -> 6 | O34: =N34+1 -> 7 | P34: =O34+1 -> 8 | ... AB34: =AA34+1 -> 20
G35: Tariff escalation factor | H35: =IF(OR(H34=0,H34>Assumptions!$B$20),0,(1+Assumptions!$B$24)^(H34-1)) -> 0 | I35: =IF(OR(I34=0,I34>Assumptions!$B$20),0,(1+Assumptions!$B$24)^(I34-1)) -> 1 | J35: =IF(OR(J34=0,J34>Assumptions!$B$20),0,(1+Assumptions!$B$24)^(J34-1)) -> 1.015 | K35: =IF(OR(K34=0,K34>Assumptions!$B$20),0,(1+Assumptions!$B$24)^(K34-1)) -> 1.030225 | L35: =IF(OR(L34=0,L34>Assumptions!$B$20),0,(1+Assumptions!$B$24)^(L34-1)) -> 1.0456784 | M35: =IF(OR(M34=0,M34>Assumptions!$B$20),0,(1+Assumptions!$B$24)^(M34-1)) -> 1.0613636 | N35: =IF(OR(N34=0,N34>Assumptions!$B$20),0,(1+Assumptions!$B$24)^(N34-1)) -> 1.077284 | O35: =IF(OR(O34=0,O34>Assumptions!$B$20),0,(1+Assumptions!$B$24)^(O34-1)) -> 1.0934433 | ... AB35: =IF(OR(AB34=0,AB34>Assumptions!$B$20),0,(1+Assumptions!$B$24)^(AB34-1)) -> 1.3269507
G36: Operating cost (USD m) | H36: =IF(OR(H34=0,H34>Assumptions!$B$20),0,Assumptions!$B$26*(1+Assumptions!$B$27)^(H34-1)) -> 0 | I36: =IF(OR(I34=0,I34>Assumptions!$B$20),0,Assumptions!$B$26*(1+Assumptions!$B$27)^(I34-1)) -> 1.2 | J36: =IF(OR(J34=0,J34>Assumptions!$B$20),0,Assumptions!$B$26*(1+Assumptions!$B$27)^(J34-1)) -> 1.236 | K36: =IF(OR(K34=0,K34>Assumptions!$B$20),0,Assumptions!$B$26*(1+Assumptions!$B$27)^(K34-1)) -> 1.27308 | L36: =IF(OR(L34=0,L34>Assumptions!$B$20),0,Assumptions!$B$26*(1+Assumptions!$B$27)^(L34-1)) -> 1.3112724 | M36: =IF(OR(M34=0,M34>Assumptions!$B$20),0,Assumptions!$B$26*(1+Assumptions!$B$27)^(M34-1)) -> 1.3506106 | N36: =IF(OR(N34=0,N34>Assumptions!$B$20),0,Assumptions!$B$26*(1+Assumptions!$B$27)^(N34-1)) -> 1.3911289 | O36: =IF(OR(O34=0,O34>Assumptions!$B$20),0,Assumptions!$B$26*(1+Assumptions!$B$27)^(O34-1)) -> 1.4328628 | ... AB36: =IF(OR(AB34=0,AB34>Assumptions!$B$20),0,Assumptions!$B$26*(1+Assumptions!$B$27)^(AB34-1)) -> 2.1042073
G37: Depreciation (USD m) | H37: =IF(AND(H34>=1,H34<=Assumptions!$B$31),Assumptions!$B$15/Assumptions!$B$31,0) -> 0 | I37: =IF(AND(I34>=1,I34<=Assumptions!$B$31),Assumptions!$B$15/Assumptions!$B$31,0) -> 3 | J37: =IF(AND(J34>=1,J34<=Assumptions!$B$31),Assumptions!$B$15/Assumptions!$B$31,0) -> 3 | K37: =IF(AND(K34>=1,K34<=Assumptions!$B$31),Assumptions!$B$15/Assumptions!$B$31,0) -> 3 | L37: =IF(AND(L34>=1,L34<=Assumptions!$B$31),Assumptions!$B$15/Assumptions!$B$31,0) -> 3 | M37: =IF(AND(M34>=1,M34<=Assumptions!$B$31),Assumptions!$B$15/Assumptions!$B$31,0) -> 3 | N37: =IF(AND(N34>=1,N34<=Assumptions!$B$31),Assumptions!$B$15/Assumptions!$B$31,0) -> 3 | O37: =IF(AND(O34>=1,O34<=Assumptions!$B$31),Assumptions!$B$15/Assumptions!$B$31,0) -> 3 | ... AB37: =IF(AND(AB34>=1,AB34<=Assumptions!$B$31),Assumptions!$B$15/Assumptions!$B$31,0) -> 3
G38: Capex (USD m) | H38: =IF(H34=0,-Assumptions!$B$15,0) -> -60 | I38: =IF(I34=0,-Assumptions!$B$15,0) -> 0 | J38: =IF(J34=0,-Assumptions!$B$15,0) -> 0 | K38: =IF(K34=0,-Assumptions!$B$15,0) -> 0 | L38: =IF(L34=0,-Assumptions!$B$15,0) -> 0 | M38: =IF(M34=0,-Assumptions!$B$15,0) -> 0 | N38: =IF(N34=0,-Assumptions!$B$15,0) -> 0 | O38: =IF(O34=0,-Assumptions!$B$15,0) -> 0 | ... AB38: =IF(AB34=0,-Assumptions!$B$15,0) -> 0
A40: Scenario # | B40: Capacity factor | C40: Net gen (GWh) | D40: Tariff (USD/kWh) | E40: Project IRR | F40: NPV @ WACC | H40: Unlevered free cash flow by year (USD m)
A41: =ROW()-40 -> 1 | B41: {=INDEX($B$12:$B$18,ROUNDUP((ROW()-40)/7,0))} -> 0.165 | C41: =Assumptions!$B$10*$B41 -> 72.27 | D41: {=INDEX($C$11:$I$11,MOD(ROW()-41,7)+1)} -> 0.06 | E41: =IRR(H41:AB41) -> 0.0085171816 | F41: =H41+NPV(Assumptions!$B$34,I41:AB41) -> -32.555476 | H41: =H$38+IF(H$35=0,0,($C41*$D41*H$35)-H$36-MAX(0,($C41*$D41*H$35)-H$36-H$37)*Assumptions!$B$33) -> -60 | I41: =I$38+IF(I$35=0,0,($C41*$D41*I$35)-I$36-MAX(0,($C41*$D41*I$35)-I$36-I$37)*Assumptions!$B$33) -> 3.09534 | J41: =J$38+IF(J$35=0,0,($C41*$D41*J$35)-J$36-MAX(0,($C41*$D41*J$35)-J$36-J$37)*Assumptions!$B$33) -> 3.1156701 | K41: =K$38+IF(K$35=0,0,($C41*$D41*K$35)-K$36-MAX(0,($C41*$D41*K$35)-K$36-K$37)*Assumptions!$B$33) -> 3.1359272 | L41: =L$38+IF(L$35=0,0,($C41*$D41*L$35)-L$36-MAX(0,($C41*$D41*L$35)-L$36-L$37)*Assumptions!$B$33) -> 3.1560987 | M41: =M$38+IF(M$35=0,0,($C41*$D41*M$35)-M$36-MAX(0,($C41*$D41*M$35)-M$36-M$37)*Assumptions!$B$33) -> 3.1761718 | N41: =N$38+IF(N$35=0,0,($C41*$D41*N$35)-N$36-MAX(0,($C41*$D41*N$35)-N$36-N$37)*Assumptions!$B$33) -> 3.196133 | O41: =O$38+IF(O$35=0,0,($C41*$D41*O$35)-O$36-MAX(0,($C41*$D41*O$35)-O$36-O$37)*Assumptions!$B$33) -> 3.2159681 | ... AB41: =AB$38+IF(AB$35=0,0,($C41*$D41*AB$35)-AB$36-MAX(0,($C41*$D41*AB$35)-AB$36-AB$37)*Assumptions!$B$33) -> 3.4548016
A42: =ROW()-40 -> 2 | B42: {=INDEX($B$12:$B$18,ROUNDUP((ROW()-40)/7,0))} -> 0.165 | C42: =Assumptions!$B$10*$B42 -> 72.27 | D42: {=INDEX($C$11:$I$11,MOD(ROW()-41,7)+1)} -> 0.065 | E42: =IRR(H42:AB42) -> 0.016893192 | F42: =H42+NPV(Assumptions!$B$34,I42:AB42) -> -30.175417 | H42: =H$38+IF(H$35=0,0,($C42*$D42*H$35)-H$36-MAX(0,($C42*$D42*H$35)-H$36-H$37)*Assumptions!$B$33) -> -60 | I42: =I$38+IF(I$35=0,0,($C42*$D42*I$35)-I$36-MAX(0,($C42*$D42*I$35)-I$36-I$37)*Assumptions!$B$33) -> 3.348285 | J42: =J$38+IF(J$35=0,0,($C42*$D42*J$35)-J$36-MAX(0,($C42*$D42*J$35)-J$36-J$37)*Assumptions!$B$33) -> 3.3724093 | K42: =K$38+IF(K$35=0,0,($C42*$D42*K$35)-K$36-MAX(0,($C42*$D42*K$35)-K$36-K$37)*Assumptions!$B$33) -> 3.3965174 | L42: =L$38+IF(L$35=0,0,($C42*$D42*L$35)-L$36-MAX(0,($C42*$D42*L$35)-L$36-L$37)*Assumptions!$B$33) -> 3.4205978 | M42: =M$38+IF(M$35=0,0,($C42*$D42*M$35)-M$36-MAX(0,($C42*$D42*M$35)-M$36-M$37)*Assumptions!$B$33) -> 3.4446384 | N42: =N$38+IF(N$35=0,0,($C42*$D42*N$35)-N$36-MAX(0,($C42*$D42*N$35)-N$36-N$37)*Assumptions!$B$33) -> 3.4686266 | O42: =O$38+IF(O$35=0,0,($C42*$D42*O$35)-O$36-MAX(0,($C42*$D42*O$35)-O$36-O$37)*Assumptions!$B$33) -> 3.4925492 | ... AB42: =AB$38+IF(AB$35=0,0,($C42*$D42*AB$35)-AB$36-MAX(0,($C42*$D42*AB$35)-AB$36-AB$37)*Assumptions!$B$33) -> 3.7904471
A43: =ROW()-40 -> 3 | B43: {=INDEX($B$12:$B$18,ROUNDUP((ROW()-40)/7,0))} -> 0.165 | C43: =Assumptions!$B$10*$B43 -> 72.27 | D43: {=INDEX($C$11:$I$11,MOD(ROW()-41,7)+1)} -> 0.07 | E43: =IRR(H43:AB43) -> 0.024845974 | F43: =H43+NPV(Assumptions!$B$34,I43:AB43) -> -27.795357 | H43: =H$38+IF(H$35=0,0,($C43*$D43*H$35)-H$36-MAX(0,($C43*$D43*H$35)-H$36-H$37)*Assumptions!$B$33) -> -60 | I43: =I$38+IF(I$35=0,0,($C43*$D43*I$35)-I$36-MAX(0,($C43*$D43*I$35)-I$36-I$37)*Assumptions!$B$33) -> 3.60123 | J43: =J$38+IF(J$35=0,0,($C43*$D43*J$35)-J$36-MAX(0,($C43*$D43*J$35)-J$36-J$37)*Assumptions!$B$33) -> 3.6291485 | K43: =K$38+IF(K$35=0,0,($C43*$D43*K$35)-K$36-MAX(0,($C43*$D43*K$35)-K$36-K$37)*Assumptions!$B$33) -> 3.6571077 | L43: =L$38+IF(L$35=0,0,($C43*$D43*L$35)-L$36-MAX(0,($C43*$D43*L$35)-L$36-L$37)*Assumptions!$B$33) -> 3.685097 | M43: =M$38+IF(M$35=0,0,($C43*$D43*M$35)-M$36-MAX(0,($C43*$D43*M$35)-M$36-M$37)*Assumptions!$B$33) -> 3.713105 | N43: =N$38+IF(N$35=0,0,($C43*$D43*N$35)-N$36-MAX(0,($C43*$D43*N$35)-N$36-N$37)*Assumptions!$B$33) -> 3.7411202 | O43: =O$38+IF(O$35=0,0,($C43*$D43*O$35)-O$36-MAX(0,($C43*$D43*O$35)-O$36-O$37)*Assumptions!$B$33) -> 3.7691302 | ... AB43: =AB$38+IF(AB$35=0,0,($C43*$D43*AB$35)-AB$36-MAX(0,($C43*$D43*AB$35)-AB$36-AB$37)*Assumptions!$B$33) -> 4.1260927
A44: =ROW()-40 -> 4 | B44: {=INDEX($B$12:$B$18,ROUNDUP((ROW()-40)/7,0))} -> 0.165 | C44: =Assumptions!$B$10*$B44 -> 72.27 | D44: {=INDEX($C$11:$I$11,MOD(ROW()-41,7)+1)} -> 0.075 | E44: =IRR(H44:AB44) -> 0.03243855 | F44: =H44+NPV(Assumptions!$B$34,I44:AB44) -> -25.415298 | H44: =H$38+IF(H$35=0,0,($C44*$D44*H$35)-H$36-MAX(0,($C44*$D44*H$35)-H$36-H$37)*Assumptions!$B$33) -> -60 | I44: =I$38+IF(I$35=0,0,($C44*$D44*I$35)-I$36-MAX(0,($C44*$D44*I$35)-I$36-I$37)*Assumptions!$B$33) -> 3.854175 | J44: =J$38+IF(J$35=0,0,($C44*$D44*J$35)-J$36-MAX(0,($C44*$D44*J$35)-J$36-J$37)*Assumptions!$B$33) -> 3.8858876 | K44: =K$38+IF(K$35=0,0,($C44*$D44*K$35)-K$36-MAX(0,($C44*$D44*K$35)-K$36-K$37)*Assumptions!$B$33) -> 3.9176979 | L44: =L$38+IF(L$35=0,0,($C44*$D44*L$35)-L$36-MAX(0,($C44*$D44*L$35)-L$36-L$37)*Assumptions!$B$33) -> 3.9495961 | M44: =M$38+IF(M$35=0,0,($C44*$D44*M$35)-M$36-MAX(0,($C44*$D44*M$35)-M$36-M$37)*Assumptions!$B$33) -> 3.9815716 | N44: =N$38+IF(N$35=0,0,($C44*$D44*N$35)-N$36-MAX(0,($C44*$D44*N$35)-N$36-N$37)*Assumptions!$B$33) -> 4.0136138 | O44: =O$38+IF(O$35=0,0,($C44*$D44*O$35)-O$36-MAX(0,($C44*$D44*O$35)-O$36-O$37)*Assumptions!$B$33) -> 4.0457112 | ... AB44: =AB$38+IF(AB$35=0,0,($C44*$D44*AB$35)-AB$36-MAX(0,($C44*$D44*AB$35)-AB$36-AB$37)*Assumptions!$B$33) -> 4.4617383
A45: =ROW()-40 -> 5 | B45: {=INDEX($B$12:$B$18,ROUNDUP((ROW()-40)/7,0))} -> 0.165 | C45: =Assumptions!$B$10*$B45 -> 72.27 | D45: {=INDEX($C$11:$I$11,MOD(ROW()-41,7)+1)} -> 0.08 | E45: =IRR(H45:AB45) -> 0.039721017 | F45: =H45+NPV(Assumptions!$B$34,I45:AB45) -> -23.035238 | H45: =H$38+IF(H$35=0,0,($C45*$D45*H$35)-H$36-MAX(0,($C45*$D45*H$35)-H$36-H$37)*Assumptions!$B$33) -> -60 | I45: =I$38+IF(I$35=0,0,($C45*$D45*I$35)-I$36-MAX(0,($C45*$D45*I$35)-I$36-I$37)*Assumptions!$B$33) -> 4.10712 | J45: =J$38+IF(J$35=0,0,($C45*$D45*J$35)-J$36-MAX(0,($C45*$D45*J$35)-J$36-J$37)*Assumptions!$B$33) -> 4.1426268 | K45: =K$38+IF(K$35=0,0,($C45*$D45*K$35)-K$36-MAX(0,($C45*$D45*K$35)-K$36-K$37)*Assumptions!$B$33) -> 4.1782882 | L45: =L$38+IF(L$35=0,0,($C45*$D45*L$35)-L$36-MAX(0,($C45*$D45*L$35)-L$36-L$37)*Assumptions!$B$33) -> 4.2140952 | M45: =M$38+IF(M$35=0,0,($C45*$D45*M$35)-M$36-MAX(0,($C45*$D45*M$35)-M$36-M$37)*Assumptions!$B$33) -> 4.2500383 | N45: =N$38+IF(N$35=0,0,($C45*$D45*N$35)-N$36-MAX(0,($C45*$D45*N$35)-N$36-N$37)*Assumptions!$B$33) -> 4.2861074 | O45: =O$38+IF(O$35=0,0,($C45*$D45*O$35)-O$36-MAX(0,($C45*$D45*O$35)-O$36-O$37)*Assumptions!$B$33) -> 4.3222922 | ... AB45: =AB$38+IF(AB$35=0,0,($C45*$D45*AB$35)-AB$36-MAX(0,($C45*$D45*AB$35)-AB$36-AB$37)*Assumptions!$B$33) -> 4.7973838
A46: =ROW()-40 -> 6 | B46: {=INDEX($B$12:$B$18,ROUNDUP((ROW()-40)/7,0))} -> 0.165 | C46: =Assumptions!$B$10*$B46 -> 72.27 | D46: {=INDEX($C$11:$I$11,MOD(ROW()-41,7)+1)} -> 0.085 | E46: =IRR(H46:AB46) -> 0.046733887 | F46: =H46+NPV(Assumptions!$B$34,I46:AB46) -> -20.655179 | H46: =H$38+IF(H$35=0,0,($C46*$D46*H$35)-H$36-MAX(0,($C46*$D46*H$35)-H$36-H$37)*Assumptions!$B$33) -> -60 | I46: =I$38+IF(I$35=0,0,($C46*$D46*I$35)-I$36-MAX(0,($C46*$D46*I$35)-I$36-I$37)*Assumptions!$B$33) -> 4.360065 | J46: =J$38+IF(J$35=0,0,($C46*$D46*J$35)-J$36-MAX(0,($C46*$D46*J$35)-J$36-J$37)*Assumptions!$B$33) -> 4.399366 | K46: =K$38+IF(K$35=0,0,($C46*$D46*K$35)-K$36-MAX(0,($C46*$D46*K$35)-K$36-K$37)*Assumptions!$B$33) -> 4.4388785 | L46: =L$38+IF(L$35=0,0,($C46*$D46*L$35)-L$36-MAX(0,($C46*$D46*L$35)-L$36-L$37)*Assumptions!$B$33) -> 4.4785943 | M46: =M$38+IF(M$35=0,0,($C46*$D46*M$35)-M$36-MAX(0,($C46*$D46*M$35)-M$36-M$37)*Assumptions!$B$33) -> 4.5185049 | N46: =N$38+IF(N$35=0,0,($C46*$D46*N$35)-N$36-MAX(0,($C46*$D46*N$35)-N$36-N$37)*Assumptions!$B$33) -> 4.558601 | O46: =O$38+IF(O$35=0,0,($C46*$D46*O$35)-O$36-MAX(0,($C46*$D46*O$35)-O$36-O$37)*Assumptions!$B$33) -> 4.5988732 | ... AB46: =AB$38+IF(AB$35=0,0,($C46*$D46*AB$35)-AB$36-MAX(0,($C46*$D46*AB$35)-AB$36-AB$37)*Assumptions!$B$33) -> 5.1330294
A47: =ROW()-40 -> 7 | B47: {=INDEX($B$12:$B$18,ROUNDUP((ROW()-40)/7,0))} -> 0.165 | C47: =Assumptions!$B$10*$B47 -> 72.27 | D47: {=INDEX($C$11:$I$11,MOD(ROW()-41,7)+1)} -> 0.09 | E47: =IRR(H47:AB47) -> 0.053510401 | F47: =H47+NPV(Assumptions!$B$34,I47:AB47) -> -18.275119 | H47: =H$38+IF(H$35=0,0,($C47*$D47*H$35)-H$36-MAX(0,($C47*$D47*H$35)-H$36-H$37)*Assumptions!$B$33) -> -60 | I47: =I$38+IF(I$35=0,0,($C47*$D47*I$35)-I$36-MAX(0,($C47*$D47*I$35)-I$36-I$37)*Assumptions!$B$33) -> 4.61301 | J47: =J$38+IF(J$35=0,0,($C47*$D47*J$35)-J$36-MAX(0,($C47*$D47*J$35)-J$36-J$37)*Assumptions!$B$33) -> 4.6561052 | K47: =K$38+IF(K$35=0,0,($C47*$D47*K$35)-K$36-MAX(0,($C47*$D47*K$35)-K$36-K$37)*Assumptions!$B$33) -> 4.6994687 | L47: =L$38+IF(L$35=0,0,($C47*$D47*L$35)-L$36-MAX(0,($C47*$D47*L$35)-L$36-L$37)*Assumptions!$B$33) -> 4.7430934 | M47: =M$38+IF(M$35=0,0,($C47*$D47*M$35)-M$36-MAX(0,($C47*$D47*M$35)-M$36-M$37)*Assumptions!$B$33) -> 4.7869715 | N47: =N$38+IF(N$35=0,0,($C47*$D47*N$35)-N$36-MAX(0,($C47*$D47*N$35)-N$36-N$37)*Assumptions!$B$33) -> 4.8310946 | O47: =O$38+IF(O$35=0,0,($C47*$D47*O$35)-O$36-MAX(0,($C47*$D47*O$35)-O$36-O$37)*Assumptions!$B$33) -> 4.8754542 | ... AB47: =AB$38+IF(AB$35=0,0,($C47*$D47*AB$35)-AB$36-MAX(0,($C47*$D47*AB$35)-AB$36-AB$37)*Assumptions!$B$33) -> 5.4686749
A48: =ROW()-40 -> 8 | B48: {=INDEX($B$12:$B$18,ROUNDUP((ROW()-40)/7,0))} -> 0.18 | C48: =Assumptions!$B$10*$B48 -> 78.84 | D48: {=INDEX($C$11:$I$11,MOD(ROW()-41,7)+1)} -> 0.06 | E48: =IRR(H48:AB48) -> 0.017632604 | F48: =H48+NPV(Assumptions!$B$34,I48:AB48) -> -29.959048 | H48: =H$38+IF(H$35=0,0,($C48*$D48*H$35)-H$36-MAX(0,($C48*$D48*H$35)-H$36-H$37)*Assumptions!$B$33) -> -60 | I48: =I$38+IF(I$35=0,0,($C48*$D48*I$35)-I$36-MAX(0,($C48*$D48*I$35)-I$36-I$37)*Assumptions!$B$33) -> 3.37128 | J48: =J$38+IF(J$35=0,0,($C48*$D48*J$35)-J$36-MAX(0,($C48*$D48*J$35)-J$36-J$37)*Assumptions!$B$33) -> 3.3957492 | K48: =K$38+IF(K$35=0,0,($C48*$D48*K$35)-K$36-MAX(0,($C48*$D48*K$35)-K$36-K$37)*Assumptions!$B$33) -> 3.4202074 | L48: =L$38+IF(L$35=0,0,($C48*$D48*L$35)-L$36-MAX(0,($C48*$D48*L$35)-L$36-L$37)*Assumptions!$B$33) -> 3.4446432 | M48: =M$38+IF(M$35=0,0,($C48*$D48*M$35)-M$36-MAX(0,($C48*$D48*M$35)-M$36-M$37)*Assumptions!$B$33) -> 3.4690445 | N48: =N$38+IF(N$35=0,0,($C48*$D48*N$35)-N$36-MAX(0,($C48*$D48*N$35)-N$36-N$37)*Assumptions!$B$33) -> 3.4933988 | O48: =O$38+IF(O$35=0,0,($C48*$D48*O$35)-O$36-MAX(0,($C48*$D48*O$35)-O$36-O$37)*Assumptions!$B$33) -> 3.5176929 | ... AB48: =AB$38+IF(AB$35=0,0,($C48*$D48*AB$35)-AB$36-MAX(0,($C48*$D48*AB$35)-AB$36-AB$37)*Assumptions!$B$33) -> 3.8209604
A49: =ROW()-40 -> 9 | B49: {=INDEX($B$12:$B$18,ROUNDUP((ROW()-40)/7,0))} -> 0.18 | C49: =Assumptions!$B$10*$B49 -> 78.84 | D49: {=INDEX($C$11:$I$11,MOD(ROW()-41,7)+1)} -> 0.065 | E49: =IRR(H49:AB49) -> 0.026251618 | F49: =H49+NPV(Assumptions!$B$34,I49:AB49) -> -27.362619 | H49: =H$38+IF(H$35=0,0,($C49*$D49*H$35)-H$36-MAX(0,($C49*$D49*H$35)-H$36-H$37)*Assumptions!$B$33) -> -60 | I49: =I$38+IF(I$35=0,0,($C49*$D49*I$35)-I$36-MAX(0,($C49*$D49*I$35)-I$36-I$37)*Assumptions!$B$33) -> 3.64722 | J49: =J$38+IF(J$35=0,0,($C49*$D49*J$35)-J$36-MAX(0,($C49*$D49*J$35)-J$36-J$37)*Assumptions!$B$33) -> 3.6758283 | K49: =K$38+IF(K$35=0,0,($C49*$D49*K$35)-K$36-MAX(0,($C49*$D49*K$35)-K$36-K$37)*Assumptions!$B$33) -> 3.7044877 | L49: =L$38+IF(L$35=0,0,($C49*$D49*L$35)-L$36-MAX(0,($C49*$D49*L$35)-L$36-L$37)*Assumptions!$B$33) -> 3.7331877 | M49: =M$38+IF(M$35=0,0,($C49*$D49*M$35)-M$36-MAX(0,($C49*$D49*M$35)-M$36-M$37)*Assumptions!$B$33) -> 3.7619172 | N49: =N$38+IF(N$35=0,0,($C49*$D49*N$35)-N$36-MAX(0,($C49*$D49*N$35)-N$36-N$37)*Assumptions!$B$33) -> 3.7906645 | O49: =O$38+IF(O$35=0,0,($C49*$D49*O$35)-O$36-MAX(0,($C49*$D49*O$35)-O$36-O$37)*Assumptions!$B$33) -> 3.8194176 | ... AB49: =AB$38+IF(AB$35=0,0,($C49*$D49*AB$35)-AB$36-MAX(0,($C49*$D49*AB$35)-AB$36-AB$37)*Assumptions!$B$33) -> 4.1871192
A50: =ROW()-40 -> 10 | B50: {=INDEX($B$12:$B$18,ROUNDUP((ROW()-40)/7,0))} -> 0.18 | C50: =Assumptions!$B$10*$B50 -> 78.84 | D50: {=INDEX($C$11:$I$11,MOD(ROW()-41,7)+1)} -> 0.07 | E50: =IRR(H50:AB50) -> 0.034453576 | F50: =H50+NPV(Assumptions!$B$34,I50:AB50) -> -24.766191 | H50: =H$38+IF(H$35=0,0,($C50*$D50*H$35)-H$36-MAX(0,($C50*$D50*H$35)-H$36-H$37)*Assumptions!$B$33) -> -60 | I50: =I$38+IF(I$35=0,0,($C50*$D50*I$35)-I$36-MAX(0,($C50*$D50*I$35)-I$36-I$37)*Assumptions!$B$33) -> 3.92316 | J50: =J$38+IF(J$35=0,0,($C50*$D50*J$35)-J$36-MAX(0,($C50*$D50*J$35)-J$36-J$37)*Assumptions!$B$33) -> 3.9559074 | K50: =K$38+IF(K$35=0,0,($C50*$D50*K$35)-K$36-MAX(0,($C50*$D50*K$35)-K$36-K$37)*Assumptions!$B$33) -> 3.988768 | L50: =L$38+IF(L$35=0,0,($C50*$D50*L$35)-L$36-MAX(0,($C50*$D50*L$35)-L$36-L$37)*Assumptions!$B$33) -> 4.0217322 | M50: =M$38+IF(M$35=0,0,($C50*$D50*M$35)-M$36-MAX(0,($C50*$D50*M$35)-M$36-M$37)*Assumptions!$B$33) -> 4.0547898 | N50: =N$38+IF(N$35=0,0,($C50*$D50*N$35)-N$36-MAX(0,($C50*$D50*N$35)-N$36-N$37)*Assumptions!$B$33) -> 4.0879303 | O50: =O$38+IF(O$35=0,0,($C50*$D50*O$35)-O$36-MAX(0,($C50*$D50*O$35)-O$36-O$37)*Assumptions!$B$33) -> 4.1211424 | ... AB50: =AB$38+IF(AB$35=0,0,($C50*$D50*AB$35)-AB$36-MAX(0,($C50*$D50*AB$35)-AB$36-AB$37)*Assumptions!$B$33) -> 4.553278
A51: =ROW()-40 -> 11 | B51: {=INDEX($B$12:$B$18,ROUNDUP((ROW()-40)/7,0))} -> 0.18 | C51: =Assumptions!$B$10*$B51 -> 78.84 | D51: {=INDEX($C$11:$I$11,MOD(ROW()-41,7)+1)} -> 0.075 | E51: =IRR(H51:AB51) -> 0.042300459 | F51: =H51+NPV(Assumptions!$B$34,I51:AB51) -> -22.169762 | H51: =H$38+IF(H$35=0,0,($C51*$D51*H$35)-H$36-MAX(0,($C51*$D51*H$35)-H$36-H$37)*Assumptions!$B$33) -> -60 | I51: =I$38+IF(I$35=0,0,($C51*$D51*I$35)-I$36-MAX(0,($C51*$D51*I$35)-I$36-I$37)*Assumptions!$B$33) -> 4.1991 | J51: =J$38+IF(J$35=0,0,($C51*$D51*J$35)-J$36-MAX(0,($C51*$D51*J$35)-J$36-J$37)*Assumptions!$B$33) -> 4.2359865 | K51: =K$38+IF(K$35=0,0,($C51*$D51*K$35)-K$36-MAX(0,($C51*$D51*K$35)-K$36-K$37)*Assumptions!$B$33) -> 4.2730483 | L51: =L$38+IF(L$35=0,0,($C51*$D51*L$35)-L$36-MAX(0,($C51*$D51*L$35)-L$36-L$37)*Assumptions!$B$33) -> 4.3102767 | M51: =M$38+IF(M$35=0,0,($C51*$D51*M$35)-M$36-MAX(0,($C51*$D51*M$35)-M$36-M$37)*Assumptions!$B$33) -> 4.3476625 | N51: =N$38+IF(N$35=0,0,($C51*$D51*N$35)-N$36-MAX(0,($C51*$D51*N$35)-N$36-N$37)*Assumptions!$B$33) -> 4.385196 | O51: =O$38+IF(O$35=0,0,($C51*$D51*O$35)-O$36-MAX(0,($C51*$D51*O$35)-O$36-O$37)*Assumptions!$B$33) -> 4.4228671 | ... AB51: =AB$38+IF(AB$35=0,0,($C51*$D51*AB$35)-AB$36-MAX(0,($C51*$D51*AB$35)-AB$36-AB$37)*Assumptions!$B$33) -> 4.9194367
A52: =ROW()-40 -> 12 | B52: {=INDEX($B$12:$B$18,ROUNDUP((ROW()-40)/7,0))} -> 0.18 | C52: =Assumptions!$B$10*$B52 -> 78.84 | D52: {=INDEX($C$11:$I$11,MOD(ROW()-41,7)+1)} -> 0.08 | E52: =IRR(H52:AB52) -> 0.049841645 | F52: =H52+NPV(Assumptions!$B$34,I52:AB52) -> -19.573334 | H52: =H$38+IF(H$35=0,0,($C52*$D52*H$35)-H$36-MAX(0,($C52*$D52*H$35)-H$36-H$37)*Assumptions!$B$33) -> -60 | I52: =I$38+IF(I$35=0,0,($C52*$D52*I$35)-I$36-MAX(0,($C52*$D52*I$35)-I$36-I$37)*Assumptions!$B$33) -> 4.47504 | J52: =J$38+IF(J$35=0,0,($C52*$D52*J$35)-J$36-MAX(0,($C52*$D52*J$35)-J$36-J$37)*Assumptions!$B$33) -> 4.5160656 | K52: =K$38+IF(K$35=0,0,($C52*$D52*K$35)-K$36-MAX(0,($C52*$D52*K$35)-K$36-K$37)*Assumptions!$B$33) -> 4.5573286 | L52: =L$38+IF(L$35=0,0,($C52*$D52*L$35)-L$36-MAX(0,($C52*$D52*L$35)-L$36-L$37)*Assumptions!$B$33) -> 4.5988212 | M52: =M$38+IF(M$35=0,0,($C52*$D52*M$35)-M$36-MAX(0,($C52*$D52*M$35)-M$36-M$37)*Assumptions!$B$33) -> 4.6405351 | N52: =N$38+IF(N$35=0,0,($C52*$D52*N$35)-N$36-MAX(0,($C52*$D52*N$35)-N$36-N$37)*Assumptions!$B$33) -> 4.6824617 | O52: =O$38+IF(O$35=0,0,($C52*$D52*O$35)-O$36-MAX(0,($C52*$D52*O$35)-O$36-O$37)*Assumptions!$B$33) -> 4.7245918 | ... AB52: =AB$38+IF(AB$35=0,0,($C52*$D52*AB$35)-AB$36-MAX(0,($C52*$D52*AB$35)-AB$36-AB$37)*Assumptions!$B$33) -> 5.2855955
... A89: =ROW()-40 -> 49 | B89: {=INDEX($B$12:$B$18,ROUNDUP((ROW()-40)/7,0))} -> 0.255 | C89: =Assumptions!$B$10*$B89 -> 111.69 | D89: {=INDEX($C$11:$I$11,MOD(ROW()-41,7)+1)} -> 0.09 | E89: =IRR(H89:AB89) -> 0.11174133 | F89: =H89+NPV(Assumptions!$B$34,I89:AB89) -> 5.092737 | H89: =H$38+IF(H$35=0,0,($C89*$D89*H$35)-H$36-MAX(0,($C89*$D89*H$35)-H$36-H$37)*Assumptions!$B$33) -> -60 | I89: =I$38+IF(I$35=0,0,($C89*$D89*I$35)-I$36-MAX(0,($C89*$D89*I$35)-I$36-I$37)*Assumptions!$B$33) -> 7.09647 | J89: =J$38+IF(J$35=0,0,($C89*$D89*J$35)-J$36-MAX(0,($C89*$D89*J$35)-J$36-J$37)*Assumptions!$B$33) -> 7.1768171 | K89: =K$38+IF(K$35=0,0,($C89*$D89*K$35)-K$36-MAX(0,($C89*$D89*K$35)-K$36-K$37)*Assumptions!$B$33) -> 7.2579913 | L89: =L$38+IF(L$35=0,0,($C89*$D89*L$35)-L$36-MAX(0,($C89*$D89*L$35)-L$36-L$37)*Assumptions!$B$33) -> 7.3399938 | M89: =M$38+IF(M$35=0,0,($C89*$D89*M$35)-M$36-MAX(0,($C89*$D89*M$35)-M$36-M$37)*Assumptions!$B$33) -> 7.4228254 | N89: =N$38+IF(N$35=0,0,($C89*$D89*N$35)-N$36-MAX(0,($C89*$D89*N$35)-N$36-N$37)*Assumptions!$B$33) -> 7.5064864 | O89: =O$38+IF(O$35=0,0,($C89*$D89*O$35)-O$36-MAX(0,($C89*$D89*O$35)-O$36-O$37)*Assumptions!$B$33) -> 7.5909768 | ... AB89: =AB$38+IF(AB$35=0,0,($C89*$D89*AB$35)-AB$36-MAX(0,($C89*$D89*AB$35)-AB$36-AB$37)*Assumptions!$B$33) -> 8.764104
A91: Scenario # | B91: Total capex | C91: Capacity factor | D91: Net gen (GWh) | E91: Tariff (USD/kWh) | F91: Project IRR | H91: Unlevered free cash flow by year (USD m) — capex-varying engine
A92: =ROW()-91 -> 1 | B92: {=INDEX($M$11:$S$11,MOD(ROW()-92,7)+1)} -> 45 | C92: {=INDEX($L$12:$L$18,ROUNDUP((ROW()-91)/7,0))} -> 0.165 | D92: =Assumptions!$B$10*$C92 -> 72.27 | E92: =Assumptions!$B$23 -> 0.075 | F92: =IRR(H92:AB92) -> 0.058445397 | H92: =IF(H$34=0,-$B92,IF(H$34>Assumptions!$B$20,0,($D92*$E92*H$35)-H$36-MAX(0,($D92*$E92*H$35)-H$36-$B92/Assumptions!$B$31)*Assumptions!$B$33)) -> -45 | I92: =IF(I$34=0,-$B92,IF(I$34>Assumptions!$B$20,0,($D92*$E92*I$35)-I$36-MAX(0,($D92*$E92*I$35)-I$36-$B92/Assumptions!$B$31)*Assumptions!$B$33)) -> 3.629175 | J92: =IF(J$34=0,-$B92,IF(J$34>Assumptions!$B$20,0,($D92*$E92*J$35)-J$36-MAX(0,($D92*$E92*J$35)-J$36-$B92/Assumptions!$B$31)*Assumptions!$B$33)) -> 3.6608876 | K92: =IF(K$34=0,-$B92,IF(K$34>Assumptions!$B$20,0,($D92*$E92*K$35)-K$36-MAX(0,($D92*$E92*K$35)-K$36-$B92/Assumptions!$B$31)*Assumptions!$B$33)) -> 3.6926979 | L92: =IF(L$34=0,-$B92,IF(L$34>Assumptions!$B$20,0,($D92*$E92*L$35)-L$36-MAX(0,($D92*$E92*L$35)-L$36-$B92/Assumptions!$B$31)*Assumptions!$B$33)) -> 3.7245961 | M92: =IF(M$34=0,-$B92,IF(M$34>Assumptions!$B$20,0,($D92*$E92*M$35)-M$36-MAX(0,($D92*$E92*M$35)-M$36-$B92/Assumptions!$B$31)*Assumptions!$B$33)) -> 3.7565716 | N92: =IF(N$34=0,-$B92,IF(N$34>Assumptions!$B$20,0,($D92*$E92*N$35)-N$36-MAX(0,($D92*$E92*N$35)-N$36-$B92/Assumptions!$B$31)*Assumptions!$B$33)) -> 3.7886138 | O92: =IF(O$34=0,-$B92,IF(O$34>Assumptions!$B$20,0,($D92*$E92*O$35)-O$36-MAX(0,($D92*$E92*O$35)-O$36-$B92/Assumptions!$B$31)*Assumptions!$B$33)) -> 3.8207112 | ... AB92: =IF(AB$34=0,-$B92,IF(AB$34>Assumptions!$B$20,0,($D92*$E92*AB$35)-AB$36-MAX(0,($D92*$E92*AB$35)-AB$36-$B92/Assumptions!$B$31)*Assumptions!$B$33)) -> 4.2367383
A93: =ROW()-91 -> 2 | B93: {=INDEX($M$11:$S$11,MOD(ROW()-92,7)+1)} -> 50 | C93: {=INDEX($L$12:$L$18,ROUNDUP((ROW()-91)/7,0))} -> 0.165 | D93: =Assumptions!$B$10*$C93 -> 72.27 | E93: =Assumptions!$B$23 -> 0.075 | F93: =IRR(H93:AB93) -> 0.048419863 | H93: =IF(H$34=0,-$B93,IF(H$34>Assumptions!$B$20,0,($D93*$E93*H$35)-H$36-MAX(0,($D93*$E93*H$35)-H$36-$B93/Assumptions!$B$31)*Assumptions!$B$33)) -> -50 | I93: =IF(I$34=0,-$B93,IF(I$34>Assumptions!$B$20,0,($D93*$E93*I$35)-I$36-MAX(0,($D93*$E93*I$35)-I$36-$B93/Assumptions!$B$31)*Assumptions!$B$33)) -> 3.704175 | J93: =IF(J$34=0,-$B93,IF(J$34>Assumptions!$B$20,0,($D93*$E93*J$35)-J$36-MAX(0,($D93*$E93*J$35)-J$36-$B93/Assumptions!$B$31)*Assumptions!$B$33)) -> 3.7358876 | K93: =IF(K$34=0,-$B93,IF(K$34>Assumptions!$B$20,0,($D93*$E93*K$35)-K$36-MAX(0,($D93*$E93*K$35)-K$36-$B93/Assumptions!$B$31)*Assumptions!$B$33)) -> 3.7676979 | L93: =IF(L$34=0,-$B93,IF(L$34>Assumptions!$B$20,0,($D93*$E93*L$35)-L$36-MAX(0,($D93*$E93*L$35)-L$36-$B93/Assumptions!$B$31)*Assumptions!$B$33)) -> 3.7995961 | M93: =IF(M$34=0,-$B93,IF(M$34>Assumptions!$B$20,0,($D93*$E93*M$35)-M$36-MAX(0,($D93*$E93*M$35)-M$36-$B93/Assumptions!$B$31)*Assumptions!$B$33)) -> 3.8315716 | N93: =IF(N$34=0,-$B93,IF(N$34>Assumptions!$B$20,0,($D93*$E93*N$35)-N$36-MAX(0,($D93*$E93*N$35)-N$36-$B93/Assumptions!$B$31)*Assumptions!$B$33)) -> 3.8636138 | O93: =IF(O$34=0,-$B93,IF(O$34>Assumptions!$B$20,0,($D93*$E93*O$35)-O$36-MAX(0,($D93*$E93*O$35)-O$36-$B93/Assumptions!$B$31)*Assumptions!$B$33)) -> 3.8957112 | ... AB93: =IF(AB$34=0,-$B93,IF(AB$34>Assumptions!$B$20,0,($D93*$E93*AB$35)-AB$36-MAX(0,($D93*$E93*AB$35)-AB$36-$B93/Assumptions!$B$31)*Assumptions!$B$33)) -> 4.3117383
A94: =ROW()-91 -> 3 | B94: {=INDEX($M$11:$S$11,MOD(ROW()-92,7)+1)} -> 55 | C94: {=INDEX($L$12:$L$18,ROUNDUP((ROW()-91)/7,0))} -> 0.165 | D94: =Assumptions!$B$10*$C94 -> 72.27 | E94: =Assumptions!$B$23 -> 0.075 | F94: =IRR(H94:AB94) -> 0.039859706 | H94: =IF(H$34=0,-$B94,IF(H$34>Assumptions!$B$20,0,($D94*$E94*H$35)-H$36-MAX(0,($D94*$E94*H$35)-H$36-$B94/Assumptions!$B$31)*Assumptions!$B$33)) -> -55 | I94: =IF(I$34=0,-$B94,IF(I$34>Assumptions!$B$20,0,($D94*$E94*I$35)-I$36-MAX(0,($D94*$E94*I$35)-I$36-$B94/Assumptions!$B$31)*Assumptions!$B$33)) -> 3.779175 | J94: =IF(J$34=0,-$B94,IF(J$34>Assumptions!$B$20,0,($D94*$E94*J$35)-J$36-MAX(0,($D94*$E94*J$35)-J$36-$B94/Assumptions!$B$31)*Assumptions!$B$33)) -> 3.8108876 | K94: =IF(K$34=0,-$B94,IF(K$34>Assumptions!$B$20,0,($D94*$E94*K$35)-K$36-MAX(0,($D94*$E94*K$35)-K$36-$B94/Assumptions!$B$31)*Assumptions!$B$33)) -> 3.8426979 | L94: =IF(L$34=0,-$B94,IF(L$34>Assumptions!$B$20,0,($D94*$E94*L$35)-L$36-MAX(0,($D94*$E94*L$35)-L$36-$B94/Assumptions!$B$31)*Assumptions!$B$33)) -> 3.8745961 | M94: =IF(M$34=0,-$B94,IF(M$34>Assumptions!$B$20,0,($D94*$E94*M$35)-M$36-MAX(0,($D94*$E94*M$35)-M$36-$B94/Assumptions!$B$31)*Assumptions!$B$33)) -> 3.9065716 | N94: =IF(N$34=0,-$B94,IF(N$34>Assumptions!$B$20,0,($D94*$E94*N$35)-N$36-MAX(0,($D94*$E94*N$35)-N$36-$B94/Assumptions!$B$31)*Assumptions!$B$33)) -> 3.9386138 | O94: =IF(O$34=0,-$B94,IF(O$34>Assumptions!$B$20,0,($D94*$E94*O$35)-O$36-MAX(0,($D94*$E94*O$35)-O$36-$B94/Assumptions!$B$31)*Assumptions!$B$33)) -> 3.9707112 | ... AB94: =IF(AB$34=0,-$B94,IF(AB$34>Assumptions!$B$20,0,($D94*$E94*AB$35)-AB$36-MAX(0,($D94*$E94*AB$35)-AB$36-$B94/Assumptions!$B$31)*Assumptions!$B$33)) -> 4.3867383
A95: =ROW()-91 -> 4 | B95: {=INDEX($M$11:$S$11,MOD(ROW()-92,7)+1)} -> 60 | C95: {=INDEX($L$12:$L$18,ROUNDUP((ROW()-91)/7,0))} -> 0.165 | D95: =Assumptions!$B$10*$C95 -> 72.27 | E95: =Assumptions!$B$23 -> 0.075 | F95: =IRR(H95:AB95) -> 0.03243855 | H95: =IF(H$34=0,-$B95,IF(H$34>Assumptions!$B$20,0,($D95*$E95*H$35)-H$36-MAX(0,($D95*$E95*H$35)-H$36-$B95/Assumptions!$B$31)*Assumptions!$B$33)) -> -60 | I95: =IF(I$34=0,-$B95,IF(I$34>Assumptions!$B$20,0,($D95*$E95*I$35)-I$36-MAX(0,($D95*$E95*I$35)-I$36-$B95/Assumptions!$B$31)*Assumptions!$B$33)) -> 3.854175 | J95: =IF(J$34=0,-$B95,IF(J$34>Assumptions!$B$20,0,($D95*$E95*J$35)-J$36-MAX(0,($D95*$E95*J$35)-J$36-$B95/Assumptions!$B$31)*Assumptions!$B$33)) -> 3.8858876 | K95: =IF(K$34=0,-$B95,IF(K$34>Assumptions!$B$20,0,($D95*$E95*K$35)-K$36-MAX(0,($D95*$E95*K$35)-K$36-$B95/Assumptions!$B$31)*Assumptions!$B$33)) -> 3.9176979 | L95: =IF(L$34=0,-$B95,IF(L$34>Assumptions!$B$20,0,($D95*$E95*L$35)-L$36-MAX(0,($D95*$E95*L$35)-L$36-$B95/Assumptions!$B$31)*Assumptions!$B$33)) -> 3.9495961 | M95: =IF(M$34=0,-$B95,IF(M$34>Assumptions!$B$20,0,($D95*$E95*M$35)-M$36-MAX(0,($D95*$E95*M$35)-M$36-$B95/Assumptions!$B$31)*Assumptions!$B$33)) -> 3.9815716 | N95: =IF(N$34=0,-$B95,IF(N$34>Assumptions!$B$20,0,($D95*$E95*N$35)-N$36-MAX(0,($D95*$E95*N$35)-N$36-$B95/Assumptions!$B$31)*Assumptions!$B$33)) -> 4.0136138 | O95: =IF(O$34=0,-$B95,IF(O$34>Assumptions!$B$20,0,($D95*$E95*O$35)-O$36-MAX(0,($D95*$E95*O$35)-O$36-$B95/Assumptions!$B$31)*Assumptions!$B$33)) -> 4.0457112 | ... AB95: =IF(AB$34=0,-$B95,IF(AB$34>Assumptions!$B$20,0,($D95*$E95*AB$35)-AB$36-MAX(0,($D95*$E95*AB$35)-AB$36-$B95/Assumptions!$B$31)*Assumptions!$B$33)) -> 4.4617383
A96: =ROW()-91 -> 5 | B96: {=INDEX($M$11:$S$11,MOD(ROW()-92,7)+1)} -> 65 | C96: {=INDEX($L$12:$L$18,ROUNDUP((ROW()-91)/7,0))} -> 0.165 | D96: =Assumptions!$B$10*$C96 -> 72.27 | E96: =Assumptions!$B$23 -> 0.075 | F96: =IRR(H96:AB96) -> 0.025924153 | H96: =IF(H$34=0,-$B96,IF(H$34>Assumptions!$B$20,0,($D96*$E96*H$35)-H$36-MAX(0,($D96*$E96*H$35)-H$36-$B96/Assumptions!$B$31)*Assumptions!$B$33)) -> -65 | I96: =IF(I$34=0,-$B96,IF(I$34>Assumptions!$B$20,0,($D96*$E96*I$35)-I$36-MAX(0,($D96*$E96*I$35)-I$36-$B96/Assumptions!$B$31)*Assumptions!$B$33)) -> 3.929175 | J96: =IF(J$34=0,-$B96,IF(J$34>Assumptions!$B$20,0,($D96*$E96*J$35)-J$36-MAX(0,($D96*$E96*J$35)-J$36-$B96/Assumptions!$B$31)*Assumptions!$B$33)) -> 3.9608876 | K96: =IF(K$34=0,-$B96,IF(K$34>Assumptions!$B$20,0,($D96*$E96*K$35)-K$36-MAX(0,($D96*$E96*K$35)-K$36-$B96/Assumptions!$B$31)*Assumptions!$B$33)) -> 3.9926979 | L96: =IF(L$34=0,-$B96,IF(L$34>Assumptions!$B$20,0,($D96*$E96*L$35)-L$36-MAX(0,($D96*$E96*L$35)-L$36-$B96/Assumptions!$B$31)*Assumptions!$B$33)) -> 4.0245961 | M96: =IF(M$34=0,-$B96,IF(M$34>Assumptions!$B$20,0,($D96*$E96*M$35)-M$36-MAX(0,($D96*$E96*M$35)-M$36-$B96/Assumptions!$B$31)*Assumptions!$B$33)) -> 4.0565716 | N96: =IF(N$34=0,-$B96,IF(N$34>Assumptions!$B$20,0,($D96*$E96*N$35)-N$36-MAX(0,($D96*$E96*N$35)-N$36-$B96/Assumptions!$B$31)*Assumptions!$B$33)) -> 4.0886138 | O96: =IF(O$34=0,-$B96,IF(O$34>Assumptions!$B$20,0,($D96*$E96*O$35)-O$36-MAX(0,($D96*$E96*O$35)-O$36-$B96/Assumptions!$B$31)*Assumptions!$B$33)) -> 4.1207112 | ... AB96: =IF(AB$34=0,-$B96,IF(AB$34>Assumptions!$B$20,0,($D96*$E96*AB$35)-AB$36-MAX(0,($D96*$E96*AB$35)-AB$36-$B96/Assumptions!$B$31)*Assumptions!$B$33)) -> 4.5367383
A97: =ROW()-91 -> 6 | B97: {=INDEX($M$11:$S$11,MOD(ROW()-92,7)+1)} -> 70 | C97: {=INDEX($L$12:$L$18,ROUNDUP((ROW()-91)/7,0))} -> 0.165 | D97: =Assumptions!$B$10*$C97 -> 72.27 | E97: =Assumptions!$B$23 -> 0.075 | F97: =IRR(H97:AB97) -> 0.020146043 | H97: =IF(H$34=0,-$B97,IF(H$34>Assumptions!$B$20,0,($D97*$E97*H$35)-H$36-MAX(0,($D97*$E97*H$35)-H$36-$B97/Assumptions!$B$31)*Assumptions!$B$33)) -> -70 | I97: =IF(I$34=0,-$B97,IF(I$34>Assumptions!$B$20,0,($D97*$E97*I$35)-I$36-MAX(0,($D97*$E97*I$35)-I$36-$B97/Assumptions!$B$31)*Assumptions!$B$33)) -> 4.004175 | J97: =IF(J$34=0,-$B97,IF(J$34>Assumptions!$B$20,0,($D97*$E97*J$35)-J$36-MAX(0,($D97*$E97*J$35)-J$36-$B97/Assumptions!$B$31)*Assumptions!$B$33)) -> 4.0358876 | K97: =IF(K$34=0,-$B97,IF(K$34>Assumptions!$B$20,0,($D97*$E97*K$35)-K$36-MAX(0,($D97*$E97*K$35)-K$36-$B97/Assumptions!$B$31)*Assumptions!$B$33)) -> 4.0676979 | L97: =IF(L$34=0,-$B97,IF(L$34>Assumptions!$B$20,0,($D97*$E97*L$35)-L$36-MAX(0,($D97*$E97*L$35)-L$36-$B97/Assumptions!$B$31)*Assumptions!$B$33)) -> 4.0995961 | M97: =IF(M$34=0,-$B97,IF(M$34>Assumptions!$B$20,0,($D97*$E97*M$35)-M$36-MAX(0,($D97*$E97*M$35)-M$36-$B97/Assumptions!$B$31)*Assumptions!$B$33)) -> 4.1315716 | N97: =IF(N$34=0,-$B97,IF(N$34>Assumptions!$B$20,0,($D97*$E97*N$35)-N$36-MAX(0,($D97*$E97*N$35)-N$36-$B97/Assumptions!$B$31)*Assumptions!$B$33)) -> 4.1636138 | O97: =IF(O$34=0,-$B97,IF(O$34>Assumptions!$B$20,0,($D97*$E97*O$35)-O$36-MAX(0,($D97*$E97*O$35)-O$36-$B97/Assumptions!$B$31)*Assumptions!$B$33)) -> 4.1957112 | ... AB97: =IF(AB$34=0,-$B97,IF(AB$34>Assumptions!$B$20,0,($D97*$E97*AB$35)-AB$36-MAX(0,($D97*$E97*AB$35)-AB$36-$B97/Assumptions!$B$31)*Assumptions!$B$33)) -> 4.6117383
A98: =ROW()-91 -> 7 | B98: {=INDEX($M$11:$S$11,MOD(ROW()-92,7)+1)} -> 75 | C98: {=INDEX($L$12:$L$18,ROUNDUP((ROW()-91)/7,0))} -> 0.165 | D98: =Assumptions!$B$10*$C98 -> 72.27 | E98: =Assumptions!$B$23 -> 0.075 | F98: =IRR(H98:AB98) -> 0.014975799 | H98: =IF(H$34=0,-$B98,IF(H$34>Assumptions!$B$20,0,($D98*$E98*H$35)-H$36-MAX(0,($D98*$E98*H$35)-H$36-$B98/Assumptions!$B$31)*Assumptions!$B$33)) -> -75 | I98: =IF(I$34=0,-$B98,IF(I$34>Assumptions!$B$20,0,($D98*$E98*I$35)-I$36-MAX(0,($D98*$E98*I$35)-I$36-$B98/Assumptions!$B$31)*Assumptions!$B$33)) -> 4.079175 | J98: =IF(J$34=0,-$B98,IF(J$34>Assumptions!$B$20,0,($D98*$E98*J$35)-J$36-MAX(0,($D98*$E98*J$35)-J$36-$B98/Assumptions!$B$31)*Assumptions!$B$33)) -> 4.1108876 | K98: =IF(K$34=0,-$B98,IF(K$34>Assumptions!$B$20,0,($D98*$E98*K$35)-K$36-MAX(0,($D98*$E98*K$35)-K$36-$B98/Assumptions!$B$31)*Assumptions!$B$33)) -> 4.1426979 | L98: =IF(L$34=0,-$B98,IF(L$34>Assumptions!$B$20,0,($D98*$E98*L$35)-L$36-MAX(0,($D98*$E98*L$35)-L$36-$B98/Assumptions!$B$31)*Assumptions!$B$33)) -> 4.1745961 | M98: =IF(M$34=0,-$B98,IF(M$34>Assumptions!$B$20,0,($D98*$E98*M$35)-M$36-MAX(0,($D98*$E98*M$35)-M$36-$B98/Assumptions!$B$31)*Assumptions!$B$33)) -> 4.2065716 | N98: =IF(N$34=0,-$B98,IF(N$34>Assumptions!$B$20,0,($D98*$E98*N$35)-N$36-MAX(0,($D98*$E98*N$35)-N$36-$B98/Assumptions!$B$31)*Assumptions!$B$33)) -> 4.2386138 | O98: =IF(O$34=0,-$B98,IF(O$34>Assumptions!$B$20,0,($D98*$E98*O$35)-O$36-MAX(0,($D98*$E98*O$35)-O$36-$B98/Assumptions!$B$31)*Assumptions!$B$33)) -> 4.2707112 | ... AB98: =IF(AB$34=0,-$B98,IF(AB$34>Assumptions!$B$20,0,($D98*$E98*AB$35)-AB$36-MAX(0,($D98*$E98*AB$35)-AB$36-$B98/Assumptions!$B$31)*Assumptions!$B$33)) -> 4.6867383
A99: =ROW()-91 -> 8 | B99: {=INDEX($M$11:$S$11,MOD(ROW()-92,7)+1)} -> 45 | C99: {=INDEX($L$12:$L$18,ROUNDUP((ROW()-91)/7,0))} -> 0.18 | D99: =Assumptions!$B$10*$C99 -> 78.84 | E99: =Assumptions!$B$23 -> 0.075 | F99: =IRR(H99:AB99) -> 0.070042992 | H99: =IF(H$34=0,-$B99,IF(H$34>Assumptions!$B$20,0,($D99*$E99*H$35)-H$36-MAX(0,($D99*$E99*H$35)-H$36-$B99/Assumptions!$B$31)*Assumptions!$B$33)) -> -45 | I99: =IF(I$34=0,-$B99,IF(I$34>Assumptions!$B$20,0,($D99*$E99*I$35)-I$36-MAX(0,($D99*$E99*I$35)-I$36-$B99/Assumptions!$B$31)*Assumptions!$B$33)) -> 3.9741 | J99: =IF(J$34=0,-$B99,IF(J$34>Assumptions!$B$20,0,($D99*$E99*J$35)-J$36-MAX(0,($D99*$E99*J$35)-J$36-$B99/Assumptions!$B$31)*Assumptions!$B$33)) -> 4.0109865 | K99: =IF(K$34=0,-$B99,IF(K$34>Assumptions!$B$20,0,($D99*$E99*K$35)-K$36-MAX(0,($D99*$E99*K$35)-K$36-$B99/Assumptions!$B$31)*Assumptions!$B$33)) -> 4.0480483 | L99: =IF(L$34=0,-$B99,IF(L$34>Assumptions!$B$20,0,($D99*$E99*L$35)-L$36-MAX(0,($D99*$E99*L$35)-L$36-$B99/Assumptions!$B$31)*Assumptions!$B$33)) -> 4.0852767 | M99: =IF(M$34=0,-$B99,IF(M$34>Assumptions!$B$20,0,($D99*$E99*M$35)-M$36-MAX(0,($D99*$E99*M$35)-M$36-$B99/Assumptions!$B$31)*Assumptions!$B$33)) -> 4.1226625 | N99: =IF(N$34=0,-$B99,IF(N$34>Assumptions!$B$20,0,($D99*$E99*N$35)-N$36-MAX(0,($D99*$E99*N$35)-N$36-$B99/Assumptions!$B$31)*Assumptions!$B$33)) -> 4.160196 | O99: =IF(O$34=0,-$B99,IF(O$34>Assumptions!$B$20,0,($D99*$E99*O$35)-O$36-MAX(0,($D99*$E99*O$35)-O$36-$B99/Assumptions!$B$31)*Assumptions!$B$33)) -> 4.1978671 | ... AB99: =IF(AB$34=0,-$B99,IF(AB$34>Assumptions!$B$20,0,($D99*$E99*AB$35)-AB$36-MAX(0,($D99*$E99*AB$35)-AB$36-$B99/Assumptions!$B$31)*Assumptions!$B$33)) -> 4.6944367
A100: =ROW()-91 -> 9 | B100: {=INDEX($M$11:$S$11,MOD(ROW()-92,7)+1)} -> 50 | C100: {=INDEX($L$12:$L$18,ROUNDUP((ROW()-91)/7,0))} -> 0.18 | D100: =Assumptions!$B$10*$C100 -> 78.84 | E100: =Assumptions!$B$23 -> 0.075 | F100: =IRR(H100:AB100) -> 0.059338123 | H100: =IF(H$34=0,-$B100,IF(H$34>Assumptions!$B$20,0,($D100*$E100*H$35)-H$36-MAX(0,($D100*$E100*H$35)-H$36-$B100/Assumptions!$B$31)*Assumptions!$B$33)) -> -50 | I100: =IF(I$34=0,-$B100,IF(I$34>Assumptions!$B$20,0,($D100*$E100*I$35)-I$36-MAX(0,($D100*$E100*I$35)-I$36-$B100/Assumptions!$B$31)*Assumptions!$B$33)) -> 4.0491 | J100: =IF(J$34=0,-$B100,IF(J$34>Assumptions!$B$20,0,($D100*$E100*J$35)-J$36-MAX(0,($D100*$E100*J$35)-J$36-$B100/Assumptions!$B$31)*Assumptions!$B$33)) -> 4.0859865 | K100: =IF(K$34=0,-$B100,IF(K$34>Assumptions!$B$20,0,($D100*$E100*K$35)-K$36-MAX(0,($D100*$E100*K$35)-K$36-$B100/Assumptions!$B$31)*Assumptions!$B$33)) -> 4.1230483 | L100: =IF(L$34=0,-$B100,IF(L$34>Assumptions!$B$20,0,($D100*$E100*L$35)-L$36-MAX(0,($D100*$E100*L$35)-L$36-$B100/Assumptions!$B$31)*Assumptions!$B$33)) -> 4.1602767 | M100: =IF(M$34=0,-$B100,IF(M$34>Assumptions!$B$20,0,($D100*$E100*M$35)-M$36-MAX(0,($D100*$E100*M$35)-M$36-$B100/Assumptions!$B$31)*Assumptions!$B$33)) -> 4.1976625 | N100: =IF(N$34=0,-$B100,IF(N$34>Assumptions!$B$20,0,($D100*$E100*N$35)-N$36-MAX(0,($D100*$E100*N$35)-N$36-$B100/Assumptions!$B$31)*Assumptions!$B$33)) -> 4.235196 | O100: =IF(O$34=0,-$B100,IF(O$34>Assumptions!$B$20,0,($D100*$E100*O$35)-O$36-MAX(0,($D100*$E100*O$35)-O$36-$B100/Assumptions!$B$31)*Assumptions!$B$33)) -> 4.2728671 | ... AB100: =IF(AB$34=0,-$B100,IF(AB$34>Assumptions!$B$20,0,($D100*$E100*AB$35)-AB$36-MAX(0,($D100*$E100*AB$35)-AB$36-$B100/Assumptions!$B$31)*Assumptions!$B$33)) -> 4.7694367
A101: =ROW()-91 -> 10 | B101: {=INDEX($M$11:$S$11,MOD(ROW()-92,7)+1)} -> 55 | C101: {=INDEX($L$12:$L$18,ROUNDUP((ROW()-91)/7,0))} -> 0.18 | D101: =Assumptions!$B$10*$C101 -> 78.84 | E101: =Assumptions!$B$23 -> 0.075 | F101: =IRR(H101:AB101) -> 0.050208597 | H101: =IF(H$34=0,-$B101,IF(H$34>Assumptions!$B$20,0,($D101*$E101*H$35)-H$36-MAX(0,($D101*$E101*H$35)-H$36-$B101/Assumptions!$B$31)*Assumptions!$B$33)) -> -55 | I101: =IF(I$34=0,-$B101,IF(I$34>Assumptions!$B$20,0,($D101*$E101*I$35)-I$36-MAX(0,($D101*$E101*I$35)-I$36-$B101/Assumptions!$B$31)*Assumptions!$B$33)) -> 4.1241 | J101: =IF(J$34=0,-$B101,IF(J$34>Assumptions!$B$20,0,($D101*$E101*J$35)-J$36-MAX(0,($D101*$E101*J$35)-J$36-$B101/Assumptions!$B$31)*Assumptions!$B$33)) -> 4.1609865 | K101: =IF(K$34=0,-$B101,IF(K$34>Assumptions!$B$20,0,($D101*$E101*K$35)-K$36-MAX(0,($D101*$E101*K$35)-K$36-$B101/Assumptions!$B$31)*Assumptions!$B$33)) -> 4.1980483 | L101: =IF(L$34=0,-$B101,IF(L$34>Assumptions!$B$20,0,($D101*$E101*L$35)-L$36-MAX(0,($D101*$E101*L$35)-L$36-$B101/Assumptions!$B$31)*Assumptions!$B$33)) -> 4.2352767 | M101: =IF(M$34=0,-$B101,IF(M$34>Assumptions!$B$20,0,($D101*$E101*M$35)-M$36-MAX(0,($D101*$E101*M$35)-M$36-$B101/Assumptions!$B$31)*Assumptions!$B$33)) -> 4.2726625 | N101: =IF(N$34=0,-$B101,IF(N$34>Assumptions!$B$20,0,($D101*$E101*N$35)-N$36-MAX(0,($D101*$E101*N$35)-N$36-$B101/Assumptions!$B$31)*Assumptions!$B$33)) -> 4.310196 | O101: =IF(O$34=0,-$B101,IF(O$34>Assumptions!$B$20,0,($D101*$E101*O$35)-O$36-MAX(0,($D101*$E101*O$35)-O$36-$B101/Assumptions!$B$31)*Assumptions!$B$33)) -> 4.3478671 | ... AB101: =IF(AB$34=0,-$B101,IF(AB$34>Assumptions!$B$20,0,($D101*$E101*AB$35)-AB$36-MAX(0,($D101*$E101*AB$35)-AB$36-$B101/Assumptions!$B$31)*Assumptions!$B$33)) -> 4.8444367
A102: =ROW()-91 -> 11 | B102: {=INDEX($M$11:$S$11,MOD(ROW()-92,7)+1)} -> 60 | C102: {=INDEX($L$12:$L$18,ROUNDUP((ROW()-91)/7,0))} -> 0.18 | D102: =Assumptions!$B$10*$C102 -> 78.84 | E102: =Assumptions!$B$23 -> 0.075 | F102: =IRR(H102:AB102) -> 0.042300459 | H102: =IF(H$34=0,-$B102,IF(H$34>Assumptions!$B$20,0,($D102*$E102*H$35)-H$36-MAX(0,($D102*$E102*H$35)-H$36-$B102/Assumptions!$B$31)*Assumptions!$B$33)) -> -60 | I102: =IF(I$34=0,-$B102,IF(I$34>Assumptions!$B$20,0,($D102*$E102*I$35)-I$36-MAX(0,($D102*$E102*I$35)-I$36-$B102/Assumptions!$B$31)*Assumptions!$B$33)) -> 4.1991 | J102: =IF(J$34=0,-$B102,IF(J$34>Assumptions!$B$20,0,($D102*$E102*J$35)-J$36-MAX(0,($D102*$E102*J$35)-J$36-$B102/Assumptions!$B$31)*Assumptions!$B$33)) -> 4.2359865 | K102: =IF(K$34=0,-$B102,IF(K$34>Assumptions!$B$20,0,($D102*$E102*K$35)-K$36-MAX(0,($D102*$E102*K$35)-K$36-$B102/Assumptions!$B$31)*Assumptions!$B$33)) -> 4.2730483 | L102: =IF(L$34=0,-$B102,IF(L$34>Assumptions!$B$20,0,($D102*$E102*L$35)-L$36-MAX(0,($D102*$E102*L$35)-L$36-$B102/Assumptions!$B$31)*Assumptions!$B$33)) -> 4.3102767 | M102: =IF(M$34=0,-$B102,IF(M$34>Assumptions!$B$20,0,($D102*$E102*M$35)-M$36-MAX(0,($D102*$E102*M$35)-M$36-$B102/Assumptions!$B$31)*Assumptions!$B$33)) -> 4.3476625 | N102: =IF(N$34=0,-$B102,IF(N$34>Assumptions!$B$20,0,($D102*$E102*N$35)-N$36-MAX(0,($D102*$E102*N$35)-N$36-$B102/Assumptions!$B$31)*Assumptions!$B$33)) -> 4.385196 | O102: =IF(O$34=0,-$B102,IF(O$34>Assumptions!$B$20,0,($D102*$E102*O$35)-O$36-MAX(0,($D102*$E102*O$35)-O$36-$B102/Assumptions!$B$31)*Assumptions!$B$33)) -> 4.4228671 | ... AB102: =IF(AB$34=0,-$B102,IF(AB$34>Assumptions!$B$20,0,($D102*$E102*AB$35)-AB$36-MAX(0,($D102*$E102*AB$35)-AB$36-$B102/Assumptions!$B$31)*Assumptions!$B$33)) -> 4.9194367
A103: =ROW()-91 -> 12 | B103: {=INDEX($M$11:$S$11,MOD(ROW()-92,7)+1)} -> 65 | C103: {=INDEX($L$12:$L$18,ROUNDUP((ROW()-91)/7,0))} -> 0.18 | D103: =Assumptions!$B$10*$C103 -> 78.84 | E103: =Assumptions!$B$23 -> 0.075 | F103: =IRR(H103:AB103) -> 0.03536263 | H103: =IF(H$34=0,-$B103,IF(H$34>Assumptions!$B$20,0,($D103*$E103*H$35)-H$36-MAX(0,($D103*$E103*H$35)-H$36-$B103/Assumptions!$B$31)*Assumptions!$B$33)) -> -65 | I103: =IF(I$34=0,-$B103,IF(I$34>Assumptions!$B$20,0,($D103*$E103*I$35)-I$36-MAX(0,($D103*$E103*I$35)-I$36-$B103/Assumptions!$B$31)*Assumptions!$B$33)) -> 4.2741 | J103: =IF(J$34=0,-$B103,IF(J$34>Assumptions!$B$20,0,($D103*$E103*J$35)-J$36-MAX(0,($D103*$E103*J$35)-J$36-$B103/Assumptions!$B$31)*Assumptions!$B$33)) -> 4.3109865 | K103: =IF(K$34=0,-$B103,IF(K$34>Assumptions!$B$20,0,($D103*$E103*K$35)-K$36-MAX(0,($D103*$E103*K$35)-K$36-$B103/Assumptions!$B$31)*Assumptions!$B$33)) -> 4.3480483 | L103: =IF(L$34=0,-$B103,IF(L$34>Assumptions!$B$20,0,($D103*$E103*L$35)-L$36-MAX(0,($D103*$E103*L$35)-L$36-$B103/Assumptions!$B$31)*Assumptions!$B$33)) -> 4.3852767 | M103: =IF(M$34=0,-$B103,IF(M$34>Assumptions!$B$20,0,($D103*$E103*M$35)-M$36-MAX(0,($D103*$E103*M$35)-M$36-$B103/Assumptions!$B$31)*Assumptions!$B$33)) -> 4.4226625 | N103: =IF(N$34=0,-$B103,IF(N$34>Assumptions!$B$20,0,($D103*$E103*N$35)-N$36-MAX(0,($D103*$E103*N$35)-N$36-$B103/Assumptions!$B$31)*Assumptions!$B$33)) -> 4.460196 | O103: =IF(O$34=0,-$B103,IF(O$34>Assumptions!$B$20,0,($D103*$E103*O$35)-O$36-MAX(0,($D103*$E103*O$35)-O$36-$B103/Assumptions!$B$31)*Assumptions!$B$33)) -> 4.4978671 | ... AB103: =IF(AB$34=0,-$B103,IF(AB$34>Assumptions!$B$20,0,($D103*$E103*AB$35)-AB$36-MAX(0,($D103*$E103*AB$35)-AB$36-$B103/Assumptions!$B$31)*Assumptions!$B$33)) -> 4.9944367
... A140: =ROW()-91 -> 49 | B140: {=INDEX($M$11:$S$11,MOD(ROW()-92,7)+1)} -> 75 | C140: {=INDEX($L$12:$L$18,ROUNDUP((ROW()-91)/7,0))} -> 0.255 | D140: =Assumptions!$B$10*$C140 -> 111.69 | E140: =Assumptions!$B$23 -> 0.075 | F140: =IRR(H140:AB140) -> 0.061979964 | H140: =IF(H$34=0,-$B140,IF(H$34>Assumptions!$B$20,0,($D140*$E140*H$35)-H$36-MAX(0,($D140*$E140*H$35)-H$36-$B140/Assumptions!$B$31)*Assumptions!$B$33)) -> -75 | I140: =IF(I$34=0,-$B140,IF(I$34>Assumptions!$B$20,0,($D140*$E140*I$35)-I$36-MAX(0,($D140*$E140*I$35)-I$36-$B140/Assumptions!$B$31)*Assumptions!$B$33)) -> 6.148725 | J140: =IF(J$34=0,-$B140,IF(J$34>Assumptions!$B$20,0,($D140*$E140*J$35)-J$36-MAX(0,($D140*$E140*J$35)-J$36-$B140/Assumptions!$B$31)*Assumptions!$B$33)) -> 6.2114809 | K140: =IF(K$34=0,-$B140,IF(K$34>Assumptions!$B$20,0,($D140*$E140*K$35)-K$36-MAX(0,($D140*$E140*K$35)-K$36-$B140/Assumptions!$B$31)*Assumptions!$B$33)) -> 6.2748001 | L140: =IF(L$34=0,-$B140,IF(L$34>Assumptions!$B$20,0,($D140*$E140*L$35)-L$36-MAX(0,($D140*$E140*L$35)-L$36-$B140/Assumptions!$B$31)*Assumptions!$B$33)) -> 6.3386797 | M140: =IF(M$34=0,-$B140,IF(M$34>Assumptions!$B$20,0,($D140*$E140*M$35)-M$36-MAX(0,($D140*$E140*M$35)-M$36-$B140/Assumptions!$B$31)*Assumptions!$B$33)) -> 6.4031166 | N140: =IF(N$34=0,-$B140,IF(N$34>Assumptions!$B$20,0,($D140*$E140*N$35)-N$36-MAX(0,($D140*$E140*N$35)-N$36-$B140/Assumptions!$B$31)*Assumptions!$B$33)) -> 6.4681069 | O140: =IF(O$34=0,-$B140,IF(O$34>Assumptions!$B$20,0,($D140*$E140*O$35)-O$36-MAX(0,($D140*$E140*O$35)-O$36-$B140/Assumptions!$B$31)*Assumptions!$B$33)) -> 6.5336467 | ... AB140: =IF(AB$34=0,-$B140,IF(AB$34>Assumptions!$B$20,0,($D140*$E140*AB$35)-AB$36-MAX(0,($D140*$E140*AB$35)-AB$36-$B140/Assumptions!$B$31)*Assumptions!$B$33)) -> 7.4329292

Sheet Outputs
A1: Meridian Solar IPP — SUMMARY OF FINDINGS
A2: Every figure below is a live link to the Model, Debt or Assumptions tab. Change any input and this page updates.
A4: PROJECT ECONOMICS | B4: Unit | C4: Value
A5: Installed capacity | B5: MW | C5: =Assumptions!$B$7 -> 50
A6: Net annual generation | B6: GWh | C6: =Assumptions!$B$11 -> 91.98
A7: Total construction cost | B7: USD m | C7: =Assumptions!$B$15 -> 60
A8: Year 1 revenue | B8: USD m | C8: =Model!$D$12 -> 6.8985
A9: Year 1 EBITDA | B9: USD m | C9: =Model!$D$17 -> 5.6985
A10: Year 1 CFADS | B10: USD m | C10: =Model!$D$34 -> 4.88895
A11: Average annual CFADS (Years 1-20) | B11: USD m | C11: =AVERAGE(Model!$D$34:$W$34) -> 5.3545959
A12: Total lifetime generation | B12: GWh | C12: =Model!$C$49 -> 1839.6
A13: PROJECT IRR (unlevered) | B13: % | C13: =Model!$C$43 -> 0.060665745
A14: PROJECT NPV at 10% discount rate | B14: USD m | C14: =Model!$C$44 -> -15.678691
A15: Simple payback from COD | B15: years | C15: =Model!$C$47 -> 12
A17: FUNDING STRUCTURE — DIF SENIOR DEBT PACKAGE | B17: Unit | C17: Value
A18: Maximum debt under the 70% gearing cap | B18: USD m | C18: =Debt!$C$16 -> 42
A19: Maximum debt under the 1.30x DSCR covenant | B19: USD m | C19: =Debt!$C$15 -> 33.973835
A20: BINDING CONSTRAINT | C20: =Debt!$C$18 -> DSCR covenant binds
A21: Senior debt sized — National Infrastructure Fund | B21: USD m | C21: =Debt!$C$26 -> 33.973835
A22: Sponsor equity (incl. DSRA funding) | B22: USD m | C22: =Debt!$C$27 -> 27.906531
A23: of which: debt service reserve account | B23: USD m | C23: =Debt!$C$31 -> 1.8803654
A24: Total sources = total uses | B24: USD m | C24: =Debt!$C$28 -> 61.880365
A25: Gearing achieved (debt / construction cost) | B25: % | C25: =Debt!$C$19 -> 0.56623058
A26: Unused capacity under the gearing cap | B26: USD m | C26: =Debt!$C$22 -> 8.0261652
A28: RETURNS & COVENANT PERFORMANCE | B28: Unit | C28: Value
A29: EQUITY IRR (post-tax) | B29: % | C29: =Debt!$C$67 -> 0.060358843
A30: Project IRR (unlevered), for comparison | B30: % | C30: =Model!$C$43 -> 0.060665745
A31: Net effect of leverage on equity IRR (after tax shield) | B31: pp | C31: =(C29-C30)*100 -> -0.030690223
A32: Equity cash-on-cash multiple | B32: x | C32: =Debt!$C$74 -> 2.1729642
A33: MINIMUM DSCR across the tenor | B33: x | C33: =Debt!$C$69 -> #NAME?
A34: AVERAGE DSCR across the tenor | B34: x | C34: =Debt!$C$70 -> 1.3
A35: DSCR covenant required by the DIF | B35: x | C35: =Assumptions!$B$40 -> 1.3
A36: Headroom to covenant at the minimum | B36: x | C36: =C33-C35 -> #NAME?
A37: Debt fully repaid in operating year | B37: year | C37: =Debt!$C$72 -> 12
A38: Years repaid ahead of the 15-year tenor | B38: years | C38: =Debt!$C$73 -> 3
A39: Model integrity check (all checks pass) | B39: flag | C39: =IF(AND(Model!$C$46="ok",Debt!$C$34="ok",Debt!$C$76="ok",Debt!$C$77="ok"),"ALL CHECKS PASS","REVIEW REQUIRED") -> ALL CHECKS PASS
A41: CHART SOURCE DATA (live links — do not overwrite)
A42: Operating year | B42: CFADS | C42: Total debt service | E42: Operating year | F42: DSCR (scheduled) | G42: Covenant floor | H42: DSCR incl. cash sweep | I42: Operating year | J42: Senior debt outstanding | K42: Equity cash flow
A43: 1 | B43: {=INDEX(Model!$D$34:$W$34,$A43)} -> 4.88895 | C43: {=INDEX(Debt!$D$47:$W$47,$A43)} -> 4.3248404 | E43: =$A43 -> 1 | F43: {=IF(INDEX(Debt!$D$48:$W$48,$A43)=0,NA(),INDEX(Debt!$D$48:$W$48,$A43))} -> 1.3 | G43: =IF(ISNA(F43),NA(),Assumptions!$B$40) -> 1.3 | H43: {=IF(INDEX(Debt!$D$49:$W$49,$A43)=0,NA(),INDEX(Debt!$D$49:$W$49,$A43))} -> 1.1304348 | I43: =$A43 -> 1 | J43: {=INDEX(Debt!$D$46:$W$46,$A43)} -> 32.366901 | K43: {=INDEX(Debt!$D$63:$W$63,$A43)} -> 1.3554926
A44: =A43+1 -> 2 | B44: {=INDEX(Model!$D$34:$W$34,$A44)} -> 4.9361842 | C44: {=INDEX(Debt!$D$47:$W$47,$A44)} -> 4.3666245 | E44: =$A44 -> 2 | F44: {=IF(INDEX(Debt!$D$48:$W$48,$A44)=0,NA(),INDEX(Debt!$D$48:$W$48,$A44))} -> 1.3 | G44: =IF(ISNA(F44),NA(),Assumptions!$B$40) -> 1.3 | H44: {=IF(INDEX(Debt!$D$49:$W$49,$A44)=0,NA(),INDEX(Debt!$D$49:$W$49,$A44))} -> 1.1304348 | I44: =$A44 -> 2 | J44: {=INDEX(Debt!$D$46:$W$46,$A44)} -> 30.589629 | K44: {=INDEX(Debt!$D$63:$W$63,$A44)} -> 1.3280712
A45: =A44+1 -> 3 | B45: {=INDEX(Model!$D$34:$W$34,$A45)} -> 4.983749 | C45: {=INDEX(Debt!$D$47:$W$47,$A45)} -> 4.4087011 | E45: =$A45 -> 3 | F45: {=IF(INDEX(Debt!$D$48:$W$48,$A45)=0,NA(),INDEX(Debt!$D$48:$W$48,$A45))} -> 1.3 | G45: =IF(ISNA(F45),NA(),Assumptions!$B$40) -> 1.3 | H45: {=IF(INDEX(Debt!$D$49:$W$49,$A45)=0,NA(),INDEX(Debt!$D$49:$W$49,$A45))} -> 1.1304348 | I45: =$A45 -> 3 | J45: {=INDEX(Debt!$D$46:$W$46,$A45)} -> 28.628098 | K45: {=INDEX(Debt!$D$63:$W$63,$A45)} -> 1.2907802
A46: =A45+1 -> 4 | B46: {=INDEX(Model!$D$34:$W$34,$A46)} -> 5.0316379 | C46: {=INDEX(Debt!$D$47:$W$47,$A46)} -> 4.4510643 | E46: =$A46 -> 4 | F46: {=IF(INDEX(Debt!$D$48:$W$48,$A46)=0,NA(),INDEX(Debt!$D$48:$W$48,$A46))} -> 1.3 | G46: =IF(ISNA(F46),NA(),Assumptions!$B$40) -> 1.3 | H46: {=IF(INDEX(Debt!$D$49:$W$49,$A46)=0,NA(),INDEX(Debt!$D$49:$W$49,$A46))} -> 1.1304348 | I46: =$A46 -> 4 | J46: {=INDEX(Debt!$D$46:$W$46,$A46)} -> 26.467281 | K46: {=INDEX(Debt!$D$63:$W$63,$A46)} -> 1.2491071
A47: =A46+1 -> 5 | B47: {=INDEX(Model!$D$34:$W$34,$A47)} -> 5.0798441 | C47: {=INDEX(Debt!$D$47:$W$47,$A47)} -> 4.4937083 | E47: =$A47 -> 5 | F47: {=IF(INDEX(Debt!$D$48:$W$48,$A47)=0,NA(),INDEX(Debt!$D$48:$W$48,$A47))} -> 1.3 | G47: =IF(ISNA(F47),NA(),Assumptions!$B$40) -> 1.3 | H47: {=IF(INDEX(Debt!$D$49:$W$49,$A47)=0,NA(),INDEX(Debt!$D$49:$W$49,$A47))} -> 1.1304348 | I47: =$A47 -> 5 | J47: {=INDEX(Debt!$D$46:$W$46,$A47)} -> 24.090956 | K47: {=INDEX(Debt!$D$63:$W$63,$A47)} -> 1.2026905
A48: =A47+1 -> 6 | B48: {=INDEX(Model!$D$34:$W$34,$A48)} -> 5.1283604 | C48: {=INDEX(Debt!$D$47:$W$47,$A48)} -> 4.5366265 | E48: =$A48 -> 6 | F48: {=IF(INDEX(Debt!$D$48:$W$48,$A48)=0,NA(),INDEX(Debt!$D$48:$W$48,$A48))} -> 1.3 | G48: =IF(ISNA(F48),NA(),Assumptions!$B$40) -> 1.3 | H48: {=IF(INDEX(Debt!$D$49:$W$49,$A48)=0,NA(),INDEX(Debt!$D$49:$W$49,$A48))} -> 1.1304348 | I48: =$A48 -> 6 | J48: {=INDEX(Debt!$D$46:$W$46,$A48)} -> 21.481606 | K48: {=INDEX(Debt!$D$63:$W$63,$A48)} -> 1.1511405
A49: =A48+1 -> 7 | B49: {=INDEX(Model!$D$34:$W$34,$A49)} -> 5.1771789 | C49: {=INDEX(Debt!$D$47:$W$47,$A49)} -> 4.5798121 | E49: =$A49 -> 7 | F49: {=IF(INDEX(Debt!$D$48:$W$48,$A49)=0,NA(),INDEX(Debt!$D$48:$W$48,$A49))} -> 1.3 | G49: =IF(ISNA(F49),NA(),Assumptions!$B$40) -> 1.3 | H49: {=IF(INDEX(Debt!$D$49:$W$49,$A49)=0,NA(),INDEX(Debt!$D$49:$W$49,$A49))} -> 1.1304348 | I49: =$A49 -> 7 | J49: {=INDEX(Debt!$D$46:$W$46,$A49)} -> 18.620322 | K49: {=INDEX(Debt!$D$63:$W$63,$A49)} -> 1.0940359
A50: =A49+1 -> 8 | B50: {=INDEX(Model!$D$34:$W$34,$A50)} -> 5.2262915 | C50: {=INDEX(Debt!$D$47:$W$47,$A50)} -> 4.6232579 | E50: =$A50 -> 8 | F50: {=IF(INDEX(Debt!$D$48:$W$48,$A50)=0,NA(),INDEX(Debt!$D$48:$W$48,$A50))} -> 1.3 | G50: =IF(ISNA(F50),NA(),Assumptions!$B$40) -> 1.3 | H50: {=IF(INDEX(Debt!$D$49:$W$49,$A50)=0,NA(),INDEX(Debt!$D$49:$W$49,$A50))} -> 1.1304348 | I50: =$A50 -> 8 | J50: {=INDEX(Debt!$D$46:$W$46,$A50)} -> 15.48669 | K50: {=INDEX(Debt!$D$63:$W$63,$A50)} -> 1.0309222
A51: =A50+1 -> 9 | B51: {=INDEX(Model!$D$34:$W$34,$A51)} -> 5.2756895 | C51: {=INDEX(Debt!$D$47:$W$47,$A51)} -> 4.6669561 | E51: =$A51 -> 9 | F51: {=IF(INDEX(Debt!$D$48:$W$48,$A51)=0,NA(),INDEX(Debt!$D$48:$W$48,$A51))} -> 1.3 | G51: =IF(ISNA(F51),NA(),Assumptions!$B$40) -> 1.3 | H51: {=IF(INDEX(Debt!$D$49:$W$49,$A51)=0,NA(),INDEX(Debt!$D$49:$W$49,$A51))} -> 1.1304348 | I51: =$A51 -> 9 | J51: {=INDEX(Debt!$D$46:$W$46,$A51)} -> 12.058669 | K51: {=INDEX(Debt!$D$63:$W$63,$A51)} -> 0.96130856
A52: =A51+1 -> 10 | B52: {=INDEX(Model!$D$34:$W$34,$A52)} -> 5.3253635 | C52: {=INDEX(Debt!$D$47:$W$47,$A52)} -> 4.7108985 | E52: =$A52 -> 10 | F52: {=IF(INDEX(Debt!$D$48:$W$48,$A52)=0,NA(),INDEX(Debt!$D$48:$W$48,$A52))} -> 1.3 | G52: =IF(ISNA(F52),NA(),Assumptions!$B$40) -> 1.3 | H52: {=IF(INDEX(Debt!$D$49:$W$49,$A52)=0,NA(),INDEX(Debt!$D$49:$W$49,$A52))} -> 1.1304348 | I52: =$A52 -> 10 | J52: {=INDEX(Debt!$D$46:$W$46,$A52)} -> 8.312464 | K52: {=INDEX(Debt!$D$63:$W$63,$A52)} -> 0.88466527
A53: =A52+1 -> 11 | B53: {=INDEX(Model!$D$34:$W$34,$A53)} -> 5.3753039 | C53: {=INDEX(Debt!$D$47:$W$47,$A53)} -> 4.7550765 | E53: =$A53 -> 11 | F53: {=IF(INDEX(Debt!$D$48:$W$48,$A53)=0,NA(),INDEX(Debt!$D$48:$W$48,$A53))} -> 1.3 | G53: =IF(ISNA(F53),NA(),Assumptions!$B$40) -> 1.3 | H53: {=IF(INDEX(Debt!$D$49:$W$49,$A53)=0,NA(),INDEX(Debt!$D$49:$W$49,$A53))} -> 1.1304348 | I53: =$A53 -> 11 | J53: {=INDEX(Debt!$D$46:$W$46,$A53)} -> 4.2223847 | K53: {=INDEX(Debt!$D$63:$W$63,$A53)} -> 0.80042027
A54: =A53+1 -> 12 | B54: {=INDEX(Model!$D$34:$W$34,$A54)} -> 5.4255001 | C54: {=INDEX(Debt!$D$47:$W$47,$A54)} -> 4.5601754 | E54: =$A54 -> 12 | F54: {=IF(INDEX(Debt!$D$48:$W$48,$A54)=0,NA(),INDEX(Debt!$D$48:$W$48,$A54))} -> 1.3 | G54: =IF(ISNA(F54),NA(),Assumptions!$B$40) -> 1.3 | H54: {=IF(INDEX(Debt!$D$49:$W$49,$A54)=0,NA(),INDEX(Debt!$D$49:$W$49,$A54))} -> 1.1897569 | I54: =$A54 -> 12 | J54: {=INDEX(Debt!$D$46:$W$46,$A54)} -> 0 | K54: {=INDEX(Debt!$D$63:$W$63,$A54)} -> 3.0533927
A55: =A54+1 -> 13 | B55: {=INDEX(Model!$D$34:$W$34,$A55)} -> 5.4759412 | C55: {=INDEX(Debt!$D$47:$W$47,$A55)} -> 0 | E55: =$A55 -> 13 | F55: {=IF(INDEX(Debt!$D$48:$W$48,$A55)=0,NA(),INDEX(Debt!$D$48:$W$48,$A55))} -> #N/A | G55: =IF(ISNA(F55),NA(),Assumptions!$B$40) -> #N/A | H55: {=IF(INDEX(Debt!$D$49:$W$49,$A55)=0,NA(),INDEX(Debt!$D$49:$W$49,$A55))} -> #N/A | I55: =$A55 -> 13 | J55: {=INDEX(Debt!$D$46:$W$46,$A55)} -> 0 | K55: {=INDEX(Debt!$D$63:$W$63,$A55)} -> 5.4759412
... A62: =A61+1 -> 20 | B62: {=INDEX(Model!$D$34:$W$34,$A62)} -> 5.8348337 | C62: {=INDEX(Debt!$D$47:$W$47,$A62)} -> 0 | E62: =$A62 -> 20 | F62: {=IF(INDEX(Debt!$D$48:$W$48,$A62)=0,NA(),INDEX(Debt!$D$48:$W$48,$A62))} -> #N/A | G62: =IF(ISNA(F62),NA(),Assumptions!$B$40) -> #N/A | H62: {=IF(INDEX(Debt!$D$49:$W$49,$A62)=0,NA(),INDEX(Debt!$D$49:$W$49,$A62))} -> #N/A | I62: =$A62 -> 20 | J62: {=INDEX(Debt!$D$46:$W$46,$A62)} -> 0 | K62: {=INDEX(Debt!$D$63:$W$63,$A62)} -> 5.8348337
A64: WHAT WOULD HAVE TO BE TRUE FOR THE PROJECT TO CLEAR A 10% RETURN | B64: Unit | C64: Required
A65: Breakeven PPA tariff (vs base of 0.0750) | B65: USD/kWh | C65: =Model!$C$56 -> 0.10087955
A66: implied tariff increase required | B66: % | C66: =Model!$C$55-1 -> 0.34506061
A67: Breakeven net capacity factor (vs base of 21.0%) | B67: % | C67: =Model!$C$57 -> 0.28246273
A68: Breakeven total capex (vs base of 60.0) | B68: USD m | C68: =Model!$C$58 -> 42.025962
A69: implied capex reduction required | B69: % | C69: =C68/Assumptions!$B$15-1 -> -0.29956729
A71: NOTE TO THE DIF CREDIT COMMITTEE — IS THIS BANKABLE?
A72: Yes as a credit, no as an equity investment on these assumptions. The debt stands up: a USD 33.97m senior facility sculpted to a flat 1.30x DSCR is fully covered by a take-or-pay PPA with a single offtaker, gearing of 56.6% sits comfortably inside the 70% cap (USD 8.03m of unused headroom), the six-month DSRA and the 50% cash sweep retire the facility in Year 12 — three years inside the 15-year tenor. There is no period of covenant breach and no reliance on a refinancing.
A73: The weakness is not the financing, it is the asset. At a 0.075/kWh tariff and USD 60m of capex the project earns an unlevered IRR of only 6.07% and a negative NPV of USD 15.68m against its own 10% discount rate. Note carefully what is NOT the problem: the DIF's 8.0% coupon looks expensive against a 6.07% asset return, but interest is tax-deductible, so the effective after-tax cost of the facility is 5.60% — about 47bp cheaper than the asset return. The capital structure is efficient. Equity IRR of 6.04% lands a bare 3bp below the project IRR, and that shortfall is the opportunity cost of USD 1.88m of DSRA sitting idle for twelve years, not the pricing of the debt. See the decomposition in section 7 of the Debt tab.
A74: Recommendation: no financing structure can rescue a project whose unlevered return sits 4pp below its own discount rate. The firm should not take this to the DIF's credit committee as an approvable transaction until the tariff or the capital cost is renegotiated — the project needs roughly 0.101/kWh (+34.5%), a 28.2% capacity factor, or capex cut to about USD 42m. The debt package itself is sound and can be lifted unchanged once the underlying economics are fixed.
A76: TWO RISKS TO MITIGATE BEFORE FINANCIAL CLOSE
A77: 1. Offtaker credit and payment risk. The entire debt service rests on one counterparty under a 20-year take-or-pay PPA, and the model shows only 0.00x of DSCR headroom above the covenant — the structure is sized to exactly 1.30x, so any payment delay breaches immediately. Mitigants: a sovereign or Treasury payment guarantee, a letter of credit sized to three to six months of invoicing on top of the DSRA, and a liquidity facility or covenant reset mechanism. Alternatively, size the debt to a 1.40-1.45x sculpting target to buy genuine headroom, accepting a smaller facility.
A78: 2. Resource and capex risk. The 21% net capacity factor is a single point estimate with no degradation allowance, and the 6.07% unlevered IRR leaves no room for either a resource shortfall or a construction overrun. Grid 3 shows a USD 5m capex overrun costs roughly 0.8pp of project IRR. Mitigants: an independent P50/P90 energy yield study with the debt sized off P90 rather than P50, a fixed-price date-certain turnkey EPC contract with liquidated damages, a 5-10% contingency inside the capex line, and an inverter replacement reserve funded from operating cash from around Year 8.
A80: Note: the model deliberately excludes panel degradation, maintenance capex and any residual value — see the stated assumptions on the Assumptions tab. Degradation and an inverter replacement reserve would both reduce late-life CFADS and are the first two items to add before a real credit submission.
